{
    "issue": {
        "title": "[Dev][CI] \"ci/scripts/install_osx_sdk.sh\" unused",
        "body": "***Note**: This issue was originally created as [ARROW-17555](https://issues.apache.org/jira/browse/ARROW-17555). Please see the [migration documentation](https://gist.github.com/toddfarmer/12aa88361532d21902818a6044fda4c3) for further details.*\n\n### Original Issue Description:\n`ci/scripts/install_osx_sdk.sh` was once used on Travis macOS CI, but it has been unused for a long time.",
        "created_at": "2022-08-29T17:52:23.000Z",
        "updated_at": "2022-08-29T21:07:56.000Z",
        "labels": [
            "Migrated from Jira",
            "Component: Continuous Integration",
            "Component: Developer Tools",
            "Type: task"
        ],
        "closed": true,
        "closed_at": "2022-08-29T21:07:56.000Z"
    },
    "comments": [
        {
            "created_at": "2022-08-29T21:07:56.114Z",
            "body": "***Note**: [Comment](https://issues.apache.org/jira/browse/ARROW-17555?focusedCommentId=17597396) by Kouhei Sutou (kou):*\nhttps://github.com/apache/arrow/pull/13996 also fixed this."
        }
    ]
}