{
    "issue": {
        "title": "[CI][Crossbow] Remove alpine crossbow jobs",
        "body": "***Note**: This issue was originally created as [ARROW-6432](https://issues.apache.org/jira/browse/ARROW-6432). Please see the [migration documentation](https://gist.github.com/toddfarmer/12aa88361532d21902818a6044fda4c3) for further details.*\n\n### Original Issue Description:\nApparently we don't expect them to pass, so we shouldn't be running them and generating failures that we're supposed to know to ignore.",
        "created_at": "2019-09-03T19:30:15.000Z",
        "updated_at": "2019-09-04T19:53:05.000Z",
        "labels": [
            "Migrated from Jira",
            "Component: Continuous Integration",
            "Type: bug"
        ],
        "closed": true,
        "closed_at": "2019-09-04T19:53:02.000Z"
    },
    "comments": [
        {
            "created_at": "2019-09-04T19:53:03.012Z",
            "body": "***Note**: [Comment](https://issues.apache.org/jira/browse/ARROW-6432?focusedCommentId=16922799) by Wes McKinney (wesm):*\nIssue resolved by pull request 5275\n<https://github.com/apache/arrow/pull/5275>"
        }
    ]
}