{
    "issue": {
        "title": "[R] Ignore attributes when testing Array$create error messages",
        "body": "***Note**: This issue was originally created as [ARROW-15170](https://issues.apache.org/jira/browse/ARROW-15170). Please see the [migration documentation](https://gist.github.com/toddfarmer/12aa88361532d21902818a6044fda4c3) for further details.*\n\n### Original Issue Description:\nThis stems from failing tests for [PR-11898](https://github.com/apache/arrow/pull/11898). \r\nhttps://github.com/apache/arrow/runs/4586708957?check_suite_focus=true",
        "created_at": "2021-12-20T19:51:35.000Z",
        "updated_at": "2021-12-21T09:29:46.000Z",
        "labels": [
            "Migrated from Jira",
            "Component: R",
            "Type: enhancement"
        ],
        "closed": true,
        "closed_at": "2021-12-21T09:28:57.000Z"
    },
    "comments": [
        {
            "created_at": "2021-12-21T09:28:57.075Z",
            "body": "***Note**: [Comment](https://issues.apache.org/jira/browse/ARROW-15170?focusedCommentId=17463086) by Drago\u0219 Moldovan-Gr\u00fcnfeld (dragosmg):*\nFixed by [PR-12005](https://github.com/apache/arrow/pull/12005).\u00a0"
        }
    ]
}