{
    "expand": "operations,versionedRepresentations,editmeta,changelog,renderedFields",
    "id": "13426296",
    "self": "https://issues.apache.org/jira/rest/api/2/issue/13426296",
    "key": "ARROW-15539",
    "fields": {
        "fixVersions": [
            {
                "self": "https://issues.apache.org/jira/rest/api/2/version/12351051",
                "id": "12351051",
                "description": "",
                "name": "8.0.0",
                "archived": false,
                "released": true,
                "releaseDate": "2022-05-06"
            }
        ],
        "resolution": {
            "self": "https://issues.apache.org/jira/rest/api/2/resolution/1",
            "id": "1",
            "description": "A fix for this issue is checked into the tree and tested.",
            "name": "Fixed"
        },
        "customfield_12312322": null,
        "customfield_12312323": null,
        "customfield_12312320": null,
        "customfield_12310420": "9223372036854775807",
        "customfield_12312321": null,
        "customfield_12312328": null,
        "customfield_12312329": null,
        "customfield_12312326": null,
        "customfield_12310300": null,
        "customfield_12312327": null,
        "customfield_12312324": null,
        "customfield_12312720": null,
        "customfield_12312325": null,
        "lastViewed": null,
        "priority": {
            "self": "https://issues.apache.org/jira/rest/api/2/priority/3",
            "iconUrl": "https://issues.apache.org/jira/images/icons/priorities/major.svg",
            "name": "Major",
            "id": "3"
        },
        "labels": [
            "pull-request-available"
        ],
        "customfield_12312333": null,
        "customfield_12312334": null,
        "customfield_12313422": "false",
        "customfield_12310310": "0.0",
        "customfield_12312331": null,
        "customfield_12312332": null,
        "aggregatetimeoriginalestimate": null,
        "timeestimate": 0,
        "customfield_12312330": null,
        "versions": [],
        "customfield_12311120": null,
        "customfield_12313826": null,
        "customfield_12312339": null,
        "issuelinks": [],
        "customfield_12313825": null,
        "assignee": {
            "self": "https://issues.apache.org/jira/rest/api/2/user?username=elena%40ursacomputing.com",
            "name": "elena@ursacomputing.com",
            "key": "elena@ursacomputing.com",
            "avatarUrls": {
                "48x48": "https://issues.apache.org/jira/secure/useravatar?avatarId=10452",
                "24x24": "https://issues.apache.org/jira/secure/useravatar?size=small&avatarId=10452",
                "16x16": "https://issues.apache.org/jira/secure/useravatar?size=xsmall&avatarId=10452",
                "32x32": "https://issues.apache.org/jira/secure/useravatar?size=medium&avatarId=10452"
            },
            "displayName": "Elena Henderson",
            "active": true,
            "timeZone": "Etc/UTC"
        },
        "customfield_12312337": null,
        "customfield_12313823": null,
        "customfield_12312338": null,
        "customfield_12311920": null,
        "customfield_12313822": null,
        "customfield_12312335": null,
        "customfield_12313821": null,
        "customfield_12312336": null,
        "customfield_12313820": null,
        "status": {
            "self": "https://issues.apache.org/jira/rest/api/2/status/5",
            "description": "A resolution has been taken, and it is awaiting verification by reporter. From here issues are either reopened, or are closed.",
            "iconUrl": "https://issues.apache.org/jira/images/icons/statuses/resolved.png",
            "name": "Resolved",
            "id": "5",
            "statusCategory": {
                "self": "https://issues.apache.org/jira/rest/api/2/statuscategory/3",
                "id": 3,
                "key": "done",
                "colorName": "green",
                "name": "Done"
            }
        },
        "components": [
            {
                "self": "https://issues.apache.org/jira/rest/api/2/component/12335702",
                "id": "12335702",
                "name": "Archery"
            }
        ],
        "customfield_12312026": null,
        "customfield_12312023": null,
        "customfield_12312024": null,
        "aggregatetimeestimate": 0,
        "customfield_12312022": null,
        "customfield_12310921": null,
        "customfield_12310920": "9223372036854775807",
        "customfield_12312823": null,
        "creator": {
            "self": "https://issues.apache.org/jira/rest/api/2/user?username=elena%40ursacomputing.com",
            "name": "elena@ursacomputing.com",
            "key": "elena@ursacomputing.com",
            "avatarUrls": {
                "48x48": "https://issues.apache.org/jira/secure/useravatar?avatarId=10452",
                "24x24": "https://issues.apache.org/jira/secure/useravatar?size=small&avatarId=10452",
                "16x16": "https://issues.apache.org/jira/secure/useravatar?size=xsmall&avatarId=10452",
                "32x32": "https://issues.apache.org/jira/secure/useravatar?size=medium&avatarId=10452"
            },
            "displayName": "Elena Henderson",
            "active": true,
            "timeZone": "Etc/UTC"
        },
        "subtasks": [],
        "reporter": {
            "self": "https://issues.apache.org/jira/rest/api/2/user?username=elena%40ursacomputing.com",
            "name": "elena@ursacomputing.com",
            "key": "elena@ursacomputing.com",
            "avatarUrls": {
                "48x48": "https://issues.apache.org/jira/secure/useravatar?avatarId=10452",
                "24x24": "https://issues.apache.org/jira/secure/useravatar?size=small&avatarId=10452",
                "16x16": "https://issues.apache.org/jira/secure/useravatar?size=xsmall&avatarId=10452",
                "32x32": "https://issues.apache.org/jira/secure/useravatar?size=medium&avatarId=10452"
            },
            "displayName": "Elena Henderson",
            "active": true,
            "timeZone": "Etc/UTC"
        },
        "aggregateprogress": {
            "progress": 4800,
            "total": 4800,
            "percent": 100
        },
        "customfield_12313520": null,
        "customfield_12310250": null,
        "progress": {
            "progress": 4800,
            "total": 4800,
            "percent": 100
        },
        "customfield_12313924": null,
        "votes": {
            "self": "https://issues.apache.org/jira/rest/api/2/issue/ARROW-15539/votes",
            "votes": 0,
            "hasVoted": false
        },
        "worklog": {
            "startAt": 0,
            "maxResults": 20,
            "total": 8,
            "worklogs": [
                {
                    "self": "https://issues.apache.org/jira/rest/api/2/issue/13426296/worklog/719809",
                    "author": {
                        "self": "https://issues.apache.org/jira/rest/api/2/user?username=githubbot",
                        "name": "githubbot",
                        "key": "githubbot",
                        "avatarUrls": {
                            "48x48": "https://issues.apache.org/jira/secure/useravatar?avatarId=10452",
                            "24x24": "https://issues.apache.org/jira/secure/useravatar?size=small&avatarId=10452",
                            "16x16": "https://issues.apache.org/jira/secure/useravatar?size=xsmall&avatarId=10452",
                            "32x32": "https://issues.apache.org/jira/secure/useravatar?size=medium&avatarId=10452"
                        },
                        "displayName": "ASF GitHub Bot",
                        "active": true,
                        "timeZone": "Etc/UTC"
                    },
                    "updateAuthor": {
                        "self": "https://issues.apache.org/jira/rest/api/2/user?username=githubbot",
                        "name": "githubbot",
                        "key": "githubbot",
                        "avatarUrls": {
                            "48x48": "https://issues.apache.org/jira/secure/useravatar?avatarId=10452",
                            "24x24": "https://issues.apache.org/jira/secure/useravatar?size=small&avatarId=10452",
                            "16x16": "https://issues.apache.org/jira/secure/useravatar?size=xsmall&avatarId=10452",
                            "32x32": "https://issues.apache.org/jira/secure/useravatar?size=medium&avatarId=10452"
                        },
                        "displayName": "ASF GitHub Bot",
                        "active": true,
                        "timeZone": "Etc/UTC"
                    },
                    "comment": "github-actions[bot] commented on pull request #12325:\nURL: https://github.com/apache/arrow/pull/12325#issuecomment-1028505766\n\n\n\n\n\n\n-- \nThis is an automated message from the Apache Git Service.\nTo respond to the message, please log on to GitHub and use the\nURL above to go to the specific comment.\n\nTo unsubscribe, e-mail: github-unsubscribe@arrow.apache.org\n\nFor queries about this service, please contact Infrastructure at:\nusers@infra.apache.org\n",
                    "created": "2022-02-03T01:04:37.125+0000",
                    "updated": "2022-02-03T01:04:37.125+0000",
                    "started": "2022-02-03T01:04:37.125+0000",
                    "timeSpent": "10m",
                    "timeSpentSeconds": 600,
                    "id": "719809",
                    "issueId": "13426296"
                },
                {
                    "self": "https://issues.apache.org/jira/rest/api/2/issue/13426296/worklog/719870",
                    "author": {
                        "self": "https://issues.apache.org/jira/rest/api/2/user?username=githubbot",
                        "name": "githubbot",
                        "key": "githubbot",
                        "avatarUrls": {
                            "48x48": "https://issues.apache.org/jira/secure/useravatar?avatarId=10452",
                            "24x24": "https://issues.apache.org/jira/secure/useravatar?size=small&avatarId=10452",
                            "16x16": "https://issues.apache.org/jira/secure/useravatar?size=xsmall&avatarId=10452",
                            "32x32": "https://issues.apache.org/jira/secure/useravatar?size=medium&avatarId=10452"
                        },
                        "displayName": "ASF GitHub Bot",
                        "active": true,
                        "timeZone": "Etc/UTC"
                    },
                    "updateAuthor": {
                        "self": "https://issues.apache.org/jira/rest/api/2/user?username=githubbot",
                        "name": "githubbot",
                        "key": "githubbot",
                        "avatarUrls": {
                            "48x48": "https://issues.apache.org/jira/secure/useravatar?avatarId=10452",
                            "24x24": "https://issues.apache.org/jira/secure/useravatar?size=small&avatarId=10452",
                            "16x16": "https://issues.apache.org/jira/secure/useravatar?size=xsmall&avatarId=10452",
                            "32x32": "https://issues.apache.org/jira/secure/useravatar?size=medium&avatarId=10452"
                        },
                        "displayName": "ASF GitHub Bot",
                        "active": true,
                        "timeZone": "Etc/UTC"
                    },
                    "comment": "jonkeane closed pull request #12325:\nURL: https://github.com/apache/arrow/pull/12325\n\n\n   \n\n\n-- \nThis is an automated message from the Apache Git Service.\nTo respond to the message, please log on to GitHub and use the\nURL above to go to the specific comment.\n\nTo unsubscribe, e-mail: github-unsubscribe@arrow.apache.org\n\nFor queries about this service, please contact Infrastructure at:\nusers@infra.apache.org\n",
                    "created": "2022-02-03T03:48:45.559+0000",
                    "updated": "2022-02-03T03:48:45.559+0000",
                    "started": "2022-02-03T03:48:45.559+0000",
                    "timeSpent": "10m",
                    "timeSpentSeconds": 600,
                    "id": "719870",
                    "issueId": "13426296"
                },
                {
                    "self": "https://issues.apache.org/jira/rest/api/2/issue/13426296/worklog/719873",
                    "author": {
                        "self": "https://issues.apache.org/jira/rest/api/2/user?username=githubbot",
                        "name": "githubbot",
                        "key": "githubbot",
                        "avatarUrls": {
                            "48x48": "https://issues.apache.org/jira/secure/useravatar?avatarId=10452",
                            "24x24": "https://issues.apache.org/jira/secure/useravatar?size=small&avatarId=10452",
                            "16x16": "https://issues.apache.org/jira/secure/useravatar?size=xsmall&avatarId=10452",
                            "32x32": "https://issues.apache.org/jira/secure/useravatar?size=medium&avatarId=10452"
                        },
                        "displayName": "ASF GitHub Bot",
                        "active": true,
                        "timeZone": "Etc/UTC"
                    },
                    "updateAuthor": {
                        "self": "https://issues.apache.org/jira/rest/api/2/user?username=githubbot",
                        "name": "githubbot",
                        "key": "githubbot",
                        "avatarUrls": {
                            "48x48": "https://issues.apache.org/jira/secure/useravatar?avatarId=10452",
                            "24x24": "https://issues.apache.org/jira/secure/useravatar?size=small&avatarId=10452",
                            "16x16": "https://issues.apache.org/jira/secure/useravatar?size=xsmall&avatarId=10452",
                            "32x32": "https://issues.apache.org/jira/secure/useravatar?size=medium&avatarId=10452"
                        },
                        "displayName": "ASF GitHub Bot",
                        "active": true,
                        "timeZone": "Etc/UTC"
                    },
                    "comment": "ursabot commented on pull request #12325:\nURL: https://github.com/apache/arrow/pull/12325#issuecomment-1028576540\n\n\n   Benchmark runs are scheduled for baseline = fb5a4f6c4158178608be475a07ddeaab59fff149 and contender = c89e67d7f85556f21438f95b9f8eafe8b53294bb. c89e67d7f85556f21438f95b9f8eafe8b53294bb is a master commit associated with this PR. Results will be available as each benchmark for each run completes.\n   Conbench compare runs links:\n   [Scheduled] [ec2-t3-xlarge-us-east-2](https://conbench.ursa.dev/compare/runs/1ab735284d49440481c73833f73e2dd3...a458d1e8d3f04bf2a3e6be3bd01fe234/)\n   [Scheduled] [ursa-i9-9960x](https://conbench.ursa.dev/compare/runs/f22323f3ba0a4ca484923019f0e6f779...65635f0379a24bbcaccf3c5b20f09cee/)\n   [Scheduled] [ursa-thinkcentre-m75q](https://conbench.ursa.dev/compare/runs/65d9d2a7c22a422788f9a6d8bab001aa...1f05a53996664bd8ae45183ba29790be/)\n   Supported benchmarks:\n   ec2-t3-xlarge-us-east-2: Supported benchmark langs: Python. Runs only benchmarks with cloud = True\n   ursa-i9-9960x: Supported benchmark langs: Python, R, JavaScript\n   ursa-thinkcentre-m75q: Supported benchmark langs: C++, Java\n   \n\n\n-- \nThis is an automated message from the Apache Git Service.\nTo respond to the message, please log on to GitHub and use the\nURL above to go to the specific comment.\n\nTo unsubscribe, e-mail: github-unsubscribe@arrow.apache.org\n\nFor queries about this service, please contact Infrastructure at:\nusers@infra.apache.org\n",
                    "created": "2022-02-03T03:51:55.414+0000",
                    "updated": "2022-02-03T03:51:55.414+0000",
                    "started": "2022-02-03T03:51:55.413+0000",
                    "timeSpent": "10m",
                    "timeSpentSeconds": 600,
                    "id": "719873",
                    "issueId": "13426296"
                },
                {
                    "self": "https://issues.apache.org/jira/rest/api/2/issue/13426296/worklog/719876",
                    "author": {
                        "self": "https://issues.apache.org/jira/rest/api/2/user?username=githubbot",
                        "name": "githubbot",
                        "key": "githubbot",
                        "avatarUrls": {
                            "48x48": "https://issues.apache.org/jira/secure/useravatar?avatarId=10452",
                            "24x24": "https://issues.apache.org/jira/secure/useravatar?size=small&avatarId=10452",
                            "16x16": "https://issues.apache.org/jira/secure/useravatar?size=xsmall&avatarId=10452",
                            "32x32": "https://issues.apache.org/jira/secure/useravatar?size=medium&avatarId=10452"
                        },
                        "displayName": "ASF GitHub Bot",
                        "active": true,
                        "timeZone": "Etc/UTC"
                    },
                    "updateAuthor": {
                        "self": "https://issues.apache.org/jira/rest/api/2/user?username=githubbot",
                        "name": "githubbot",
                        "key": "githubbot",
                        "avatarUrls": {
                            "48x48": "https://issues.apache.org/jira/secure/useravatar?avatarId=10452",
                            "24x24": "https://issues.apache.org/jira/secure/useravatar?size=small&avatarId=10452",
                            "16x16": "https://issues.apache.org/jira/secure/useravatar?size=xsmall&avatarId=10452",
                            "32x32": "https://issues.apache.org/jira/secure/useravatar?size=medium&avatarId=10452"
                        },
                        "displayName": "ASF GitHub Bot",
                        "active": true,
                        "timeZone": "Etc/UTC"
                    },
                    "comment": "ursabot edited a comment on pull request #12325:\nURL: https://github.com/apache/arrow/pull/12325#issuecomment-1028576540\n\n\n   Benchmark runs are scheduled for baseline = fb5a4f6c4158178608be475a07ddeaab59fff149 and contender = c89e67d7f85556f21438f95b9f8eafe8b53294bb. c89e67d7f85556f21438f95b9f8eafe8b53294bb is a master commit associated with this PR. Results will be available as each benchmark for each run completes.\n   Conbench compare runs links:\n   [Finished :arrow_down:0.0% :arrow_up:0.0%] [ec2-t3-xlarge-us-east-2](https://conbench.ursa.dev/compare/runs/1ab735284d49440481c73833f73e2dd3...a458d1e8d3f04bf2a3e6be3bd01fe234/)\n   [Scheduled] [ursa-i9-9960x](https://conbench.ursa.dev/compare/runs/f22323f3ba0a4ca484923019f0e6f779...65635f0379a24bbcaccf3c5b20f09cee/)\n   [Scheduled] [ursa-thinkcentre-m75q](https://conbench.ursa.dev/compare/runs/65d9d2a7c22a422788f9a6d8bab001aa...1f05a53996664bd8ae45183ba29790be/)\n   Supported benchmarks:\n   ec2-t3-xlarge-us-east-2: Supported benchmark langs: Python. Runs only benchmarks with cloud = True\n   ursa-i9-9960x: Supported benchmark langs: Python, R, JavaScript\n   ursa-thinkcentre-m75q: Supported benchmark langs: C++, Java\n   \n\n\n-- \nThis is an automated message from the Apache Git Service.\nTo respond to the message, please log on to GitHub and use the\nURL above to go to the specific comment.\n\nTo unsubscribe, e-mail: github-unsubscribe@arrow.apache.org\n\nFor queries about this service, please contact Infrastructure at:\nusers@infra.apache.org\n",
                    "created": "2022-02-03T04:11:57.240+0000",
                    "updated": "2022-02-03T04:11:57.240+0000",
                    "started": "2022-02-03T04:11:57.239+0000",
                    "timeSpent": "10m",
                    "timeSpentSeconds": 600,
                    "id": "719876",
                    "issueId": "13426296"
                },
                {
                    "self": "https://issues.apache.org/jira/rest/api/2/issue/13426296/worklog/719969",
                    "author": {
                        "self": "https://issues.apache.org/jira/rest/api/2/user?username=githubbot",
                        "name": "githubbot",
                        "key": "githubbot",
                        "avatarUrls": {
                            "48x48": "https://issues.apache.org/jira/secure/useravatar?avatarId=10452",
                            "24x24": "https://issues.apache.org/jira/secure/useravatar?size=small&avatarId=10452",
                            "16x16": "https://issues.apache.org/jira/secure/useravatar?size=xsmall&avatarId=10452",
                            "32x32": "https://issues.apache.org/jira/secure/useravatar?size=medium&avatarId=10452"
                        },
                        "displayName": "ASF GitHub Bot",
                        "active": true,
                        "timeZone": "Etc/UTC"
                    },
                    "updateAuthor": {
                        "self": "https://issues.apache.org/jira/rest/api/2/user?username=githubbot",
                        "name": "githubbot",
                        "key": "githubbot",
                        "avatarUrls": {
                            "48x48": "https://issues.apache.org/jira/secure/useravatar?avatarId=10452",
                            "24x24": "https://issues.apache.org/jira/secure/useravatar?size=small&avatarId=10452",
                            "16x16": "https://issues.apache.org/jira/secure/useravatar?size=xsmall&avatarId=10452",
                            "32x32": "https://issues.apache.org/jira/secure/useravatar?size=medium&avatarId=10452"
                        },
                        "displayName": "ASF GitHub Bot",
                        "active": true,
                        "timeZone": "Etc/UTC"
                    },
                    "comment": "ursabot edited a comment on pull request #12325:\nURL: https://github.com/apache/arrow/pull/12325#issuecomment-1028576540\n\n\n   Benchmark runs are scheduled for baseline = fb5a4f6c4158178608be475a07ddeaab59fff149 and contender = c89e67d7f85556f21438f95b9f8eafe8b53294bb. c89e67d7f85556f21438f95b9f8eafe8b53294bb is a master commit associated with this PR. Results will be available as each benchmark for each run completes.\n   Conbench compare runs links:\n   [Finished :arrow_down:0.0% :arrow_up:0.0%] [ec2-t3-xlarge-us-east-2](https://conbench.ursa.dev/compare/runs/1ab735284d49440481c73833f73e2dd3...a458d1e8d3f04bf2a3e6be3bd01fe234/)\n   [Scheduled] [ursa-i9-9960x](https://conbench.ursa.dev/compare/runs/f22323f3ba0a4ca484923019f0e6f779...65635f0379a24bbcaccf3c5b20f09cee/)\n   [Finished :arrow_down:0.73% :arrow_up:0.0%] [ursa-thinkcentre-m75q](https://conbench.ursa.dev/compare/runs/65d9d2a7c22a422788f9a6d8bab001aa...1f05a53996664bd8ae45183ba29790be/)\n   Supported benchmarks:\n   ec2-t3-xlarge-us-east-2: Supported benchmark langs: Python. Runs only benchmarks with cloud = True\n   ursa-i9-9960x: Supported benchmark langs: Python, R, JavaScript\n   ursa-thinkcentre-m75q: Supported benchmark langs: C++, Java\n   \n\n\n-- \nThis is an automated message from the Apache Git Service.\nTo respond to the message, please log on to GitHub and use the\nURL above to go to the specific comment.\n\nTo unsubscribe, e-mail: github-unsubscribe@arrow.apache.org\n\nFor queries about this service, please contact Infrastructure at:\nusers@infra.apache.org\n",
                    "created": "2022-02-03T09:32:11.703+0000",
                    "updated": "2022-02-03T09:32:11.703+0000",
                    "started": "2022-02-03T09:32:11.702+0000",
                    "timeSpent": "10m",
                    "timeSpentSeconds": 600,
                    "id": "719969",
                    "issueId": "13426296"
                },
                {
                    "self": "https://issues.apache.org/jira/rest/api/2/issue/13426296/worklog/720190",
                    "author": {
                        "self": "https://issues.apache.org/jira/rest/api/2/user?username=githubbot",
                        "name": "githubbot",
                        "key": "githubbot",
                        "avatarUrls": {
                            "48x48": "https://issues.apache.org/jira/secure/useravatar?avatarId=10452",
                            "24x24": "https://issues.apache.org/jira/secure/useravatar?size=small&avatarId=10452",
                            "16x16": "https://issues.apache.org/jira/secure/useravatar?size=xsmall&avatarId=10452",
                            "32x32": "https://issues.apache.org/jira/secure/useravatar?size=medium&avatarId=10452"
                        },
                        "displayName": "ASF GitHub Bot",
                        "active": true,
                        "timeZone": "Etc/UTC"
                    },
                    "updateAuthor": {
                        "self": "https://issues.apache.org/jira/rest/api/2/user?username=githubbot",
                        "name": "githubbot",
                        "key": "githubbot",
                        "avatarUrls": {
                            "48x48": "https://issues.apache.org/jira/secure/useravatar?avatarId=10452",
                            "24x24": "https://issues.apache.org/jira/secure/useravatar?size=small&avatarId=10452",
                            "16x16": "https://issues.apache.org/jira/secure/useravatar?size=xsmall&avatarId=10452",
                            "32x32": "https://issues.apache.org/jira/secure/useravatar?size=medium&avatarId=10452"
                        },
                        "displayName": "ASF GitHub Bot",
                        "active": true,
                        "timeZone": "Etc/UTC"
                    },
                    "comment": "ursabot edited a comment on pull request #12325:\nURL: https://github.com/apache/arrow/pull/12325#issuecomment-1028576540\n\n\n   Benchmark runs are scheduled for baseline = fb5a4f6c4158178608be475a07ddeaab59fff149 and contender = c89e67d7f85556f21438f95b9f8eafe8b53294bb. c89e67d7f85556f21438f95b9f8eafe8b53294bb is a master commit associated with this PR. Results will be available as each benchmark for each run completes.\n   Conbench compare runs links:\n   [Finished :arrow_down:0.0% :arrow_up:0.0%] [ec2-t3-xlarge-us-east-2](https://conbench.ursa.dev/compare/runs/1ab735284d49440481c73833f73e2dd3...a458d1e8d3f04bf2a3e6be3bd01fe234/)\n   [Failed] [ursa-i9-9960x](https://conbench.ursa.dev/compare/runs/f22323f3ba0a4ca484923019f0e6f779...65635f0379a24bbcaccf3c5b20f09cee/)\n   [Finished :arrow_down:0.73% :arrow_up:0.0%] [ursa-thinkcentre-m75q](https://conbench.ursa.dev/compare/runs/65d9d2a7c22a422788f9a6d8bab001aa...1f05a53996664bd8ae45183ba29790be/)\n   Supported benchmarks:\n   ec2-t3-xlarge-us-east-2: Supported benchmark langs: Python. Runs only benchmarks with cloud = True\n   ursa-i9-9960x: Supported benchmark langs: Python, R, JavaScript\n   ursa-thinkcentre-m75q: Supported benchmark langs: C++, Java\n   \n\n\n-- \nThis is an automated message from the Apache Git Service.\nTo respond to the message, please log on to GitHub and use the\nURL above to go to the specific comment.\n\nTo unsubscribe, e-mail: github-unsubscribe@arrow.apache.org\n\nFor queries about this service, please contact Infrastructure at:\nusers@infra.apache.org\n",
                    "created": "2022-02-03T14:51:27.963+0000",
                    "updated": "2022-02-03T14:51:27.963+0000",
                    "started": "2022-02-03T14:51:27.963+0000",
                    "timeSpent": "10m",
                    "timeSpentSeconds": 600,
                    "id": "720190",
                    "issueId": "13426296"
                },
                {
                    "self": "https://issues.apache.org/jira/rest/api/2/issue/13426296/worklog/720444",
                    "author": {
                        "self": "https://issues.apache.org/jira/rest/api/2/user?username=githubbot",
                        "name": "githubbot",
                        "key": "githubbot",
                        "avatarUrls": {
                            "48x48": "https://issues.apache.org/jira/secure/useravatar?avatarId=10452",
                            "24x24": "https://issues.apache.org/jira/secure/useravatar?size=small&avatarId=10452",
                            "16x16": "https://issues.apache.org/jira/secure/useravatar?size=xsmall&avatarId=10452",
                            "32x32": "https://issues.apache.org/jira/secure/useravatar?size=medium&avatarId=10452"
                        },
                        "displayName": "ASF GitHub Bot",
                        "active": true,
                        "timeZone": "Etc/UTC"
                    },
                    "updateAuthor": {
                        "self": "https://issues.apache.org/jira/rest/api/2/user?username=githubbot",
                        "name": "githubbot",
                        "key": "githubbot",
                        "avatarUrls": {
                            "48x48": "https://issues.apache.org/jira/secure/useravatar?avatarId=10452",
                            "24x24": "https://issues.apache.org/jira/secure/useravatar?size=small&avatarId=10452",
                            "16x16": "https://issues.apache.org/jira/secure/useravatar?size=xsmall&avatarId=10452",
                            "32x32": "https://issues.apache.org/jira/secure/useravatar?size=medium&avatarId=10452"
                        },
                        "displayName": "ASF GitHub Bot",
                        "active": true,
                        "timeZone": "Etc/UTC"
                    },
                    "comment": "ursabot edited a comment on pull request #12325:\nURL: https://github.com/apache/arrow/pull/12325#issuecomment-1028576540\n\n\n   Benchmark runs are scheduled for baseline = fb5a4f6c4158178608be475a07ddeaab59fff149 and contender = c89e67d7f85556f21438f95b9f8eafe8b53294bb. c89e67d7f85556f21438f95b9f8eafe8b53294bb is a master commit associated with this PR. Results will be available as each benchmark for each run completes.\n   Conbench compare runs links:\n   [Finished :arrow_down:0.0% :arrow_up:0.0%] [ec2-t3-xlarge-us-east-2](https://conbench.ursa.dev/compare/runs/1ab735284d49440481c73833f73e2dd3...a458d1e8d3f04bf2a3e6be3bd01fe234/)\n   [Scheduled] [ursa-i9-9960x](https://conbench.ursa.dev/compare/runs/f22323f3ba0a4ca484923019f0e6f779...65635f0379a24bbcaccf3c5b20f09cee/)\n   [Finished :arrow_down:0.73% :arrow_up:0.0%] [ursa-thinkcentre-m75q](https://conbench.ursa.dev/compare/runs/65d9d2a7c22a422788f9a6d8bab001aa...1f05a53996664bd8ae45183ba29790be/)\n   Supported benchmarks:\n   ec2-t3-xlarge-us-east-2: Supported benchmark langs: Python. Runs only benchmarks with cloud = True\n   ursa-i9-9960x: Supported benchmark langs: Python, R, JavaScript\n   ursa-thinkcentre-m75q: Supported benchmark langs: C++, Java\n   \n\n\n-- \nThis is an automated message from the Apache Git Service.\nTo respond to the message, please log on to GitHub and use the\nURL above to go to the specific comment.\n\nTo unsubscribe, e-mail: github-unsubscribe@arrow.apache.org\n\nFor queries about this service, please contact Infrastructure at:\nusers@infra.apache.org\n",
                    "created": "2022-02-03T22:02:27.059+0000",
                    "updated": "2022-02-03T22:02:27.059+0000",
                    "started": "2022-02-03T22:02:27.059+0000",
                    "timeSpent": "10m",
                    "timeSpentSeconds": 600,
                    "id": "720444",
                    "issueId": "13426296"
                },
                {
                    "self": "https://issues.apache.org/jira/rest/api/2/issue/13426296/worklog/720623",
                    "author": {
                        "self": "https://issues.apache.org/jira/rest/api/2/user?username=githubbot",
                        "name": "githubbot",
                        "key": "githubbot",
                        "avatarUrls": {
                            "48x48": "https://issues.apache.org/jira/secure/useravatar?avatarId=10452",
                            "24x24": "https://issues.apache.org/jira/secure/useravatar?size=small&avatarId=10452",
                            "16x16": "https://issues.apache.org/jira/secure/useravatar?size=xsmall&avatarId=10452",
                            "32x32": "https://issues.apache.org/jira/secure/useravatar?size=medium&avatarId=10452"
                        },
                        "displayName": "ASF GitHub Bot",
                        "active": true,
                        "timeZone": "Etc/UTC"
                    },
                    "updateAuthor": {
                        "self": "https://issues.apache.org/jira/rest/api/2/user?username=githubbot",
                        "name": "githubbot",
                        "key": "githubbot",
                        "avatarUrls": {
                            "48x48": "https://issues.apache.org/jira/secure/useravatar?avatarId=10452",
                            "24x24": "https://issues.apache.org/jira/secure/useravatar?size=small&avatarId=10452",
                            "16x16": "https://issues.apache.org/jira/secure/useravatar?size=xsmall&avatarId=10452",
                            "32x32": "https://issues.apache.org/jira/secure/useravatar?size=medium&avatarId=10452"
                        },
                        "displayName": "ASF GitHub Bot",
                        "active": true,
                        "timeZone": "Etc/UTC"
                    },
                    "comment": "ursabot edited a comment on pull request #12325:\nURL: https://github.com/apache/arrow/pull/12325#issuecomment-1028576540\n\n\n   Benchmark runs are scheduled for baseline = fb5a4f6c4158178608be475a07ddeaab59fff149 and contender = c89e67d7f85556f21438f95b9f8eafe8b53294bb. c89e67d7f85556f21438f95b9f8eafe8b53294bb is a master commit associated with this PR. Results will be available as each benchmark for each run completes.\n   Conbench compare runs links:\n   [Finished :arrow_down:0.0% :arrow_up:0.0%] [ec2-t3-xlarge-us-east-2](https://conbench.ursa.dev/compare/runs/1ab735284d49440481c73833f73e2dd3...a458d1e8d3f04bf2a3e6be3bd01fe234/)\n   [Finished :arrow_down:0.36% :arrow_up:0.0%] [ursa-i9-9960x](https://conbench.ursa.dev/compare/runs/f22323f3ba0a4ca484923019f0e6f779...65635f0379a24bbcaccf3c5b20f09cee/)\n   [Finished :arrow_down:0.73% :arrow_up:0.0%] [ursa-thinkcentre-m75q](https://conbench.ursa.dev/compare/runs/65d9d2a7c22a422788f9a6d8bab001aa...1f05a53996664bd8ae45183ba29790be/)\n   Supported benchmarks:\n   ec2-t3-xlarge-us-east-2: Supported benchmark langs: Python. Runs only benchmarks with cloud = True\n   ursa-i9-9960x: Supported benchmark langs: Python, R, JavaScript\n   ursa-thinkcentre-m75q: Supported benchmark langs: C++, Java\n   \n\n\n-- \nThis is an automated message from the Apache Git Service.\nTo respond to the message, please log on to GitHub and use the\nURL above to go to the specific comment.\n\nTo unsubscribe, e-mail: github-unsubscribe@arrow.apache.org\n\nFor queries about this service, please contact Infrastructure at:\nusers@infra.apache.org\n",
                    "created": "2022-02-04T03:11:45.043+0000",
                    "updated": "2022-02-04T03:11:45.043+0000",
                    "started": "2022-02-04T03:11:45.043+0000",
                    "timeSpent": "10m",
                    "timeSpentSeconds": 600,
                    "id": "720623",
                    "issueId": "13426296"
                }
            ]
        },
        "customfield_12313920": null,
        "issuetype": {
            "self": "https://issues.apache.org/jira/rest/api/2/issuetype/1",
            "id": "1",
            "description": "A problem which impairs or prevents the functions of the product.",
            "iconUrl": "https://issues.apache.org/jira/secure/viewavatar?size=xsmall&avatarId=21133&avatarType=issuetype",
            "name": "Bug",
            "subtask": false,
            "avatarId": 21133
        },
        "timespent": 4800,
        "customfield_12314020": "{summaryBean=com.atlassian.jira.plugin.devstatus.rest.SummaryBean@9d3719a[summary={pullrequest=com.atlassian.jira.plugin.devstatus.rest.SummaryItemBean@74329402[overall=PullRequestOverallBean{stateCount=0, state='OPEN', details=PullRequestOverallDetails{openCount=0, mergedCount=0, declinedCount=0}},byInstanceType={}], build=com.atlassian.jira.plugin.devstatus.rest.SummaryItemBean@1152608b[overall=com.atlassian.jira.plugin.devstatus.summary.beans.BuildOverallBean@71207427[failedBuildCount=0,successfulBuildCount=0,unknownBuildCount=0,count=0,lastUpdated=<null>,lastUpdatedTimestamp=<null>],byInstanceType={}], review=com.atlassian.jira.plugin.devstatus.rest.SummaryItemBean@1cad1965[overall=com.atlassian.jira.plugin.devstatus.summary.beans.ReviewsOverallBean@63bbe525[stateCount=0,state=<null>,dueDate=<null>,overDue=false,count=0,lastUpdated=<null>,lastUpdatedTimestamp=<null>],byInstanceType={}], deployment-environment=com.atlassian.jira.plugin.devstatus.rest.SummaryItemBean@616f87e1[overall=com.atlassian.jira.plugin.devstatus.summary.beans.DeploymentOverallBean@131c56a7[topEnvironments=[],showProjects=false,successfulCount=0,count=0,lastUpdated=<null>,lastUpdatedTimestamp=<null>],byInstanceType={}], repository=com.atlassian.jira.plugin.devstatus.rest.SummaryItemBean@678e0390[overall=com.atlassian.jira.plugin.devstatus.summary.beans.CommitOverallBean@5ba04089[count=0,lastUpdated=<null>,lastUpdatedTimestamp=<null>],byInstanceType={}], branch=com.atlassian.jira.plugin.devstatus.rest.SummaryItemBean@466d9493[overall=com.atlassian.jira.plugin.devstatus.summary.beans.BranchOverallBean@37354b97[count=0,lastUpdated=<null>,lastUpdatedTimestamp=<null>],byInstanceType={}]},errors=[],configErrors=[]], devSummaryJson={\"cachedValue\":{\"errors\":[],\"configErrors\":[],\"summary\":{\"pullrequest\":{\"overall\":{\"count\":0,\"lastUpdated\":null,\"stateCount\":0,\"state\":\"OPEN\",\"details\":{\"openCount\":0,\"mergedCount\":0,\"declinedCount\":0,\"total\":0},\"open\":true},\"byInstanceType\":{}},\"build\":{\"overall\":{\"count\":0,\"lastUpdated\":null,\"failedBuildCount\":0,\"successfulBuildCount\":0,\"unknownBuildCount\":0},\"byInstanceType\":{}},\"review\":{\"overall\":{\"count\":0,\"lastUpdated\":null,\"stateCount\":0,\"state\":null,\"dueDate\":null,\"overDue\":false,\"completed\":false},\"byInstanceType\":{}},\"deployment-environment\":{\"overall\":{\"count\":0,\"lastUpdated\":null,\"topEnvironments\":[],\"showProjects\":false,\"successfulCount\":0},\"byInstanceType\":{}},\"repository\":{\"overall\":{\"count\":0,\"lastUpdated\":null},\"byInstanceType\":{}},\"branch\":{\"overall\":{\"count\":0,\"lastUpdated\":null},\"byInstanceType\":{}}}},\"isStale\":false}}",
        "customfield_12314141": null,
        "customfield_12314140": null,
        "project": {
            "self": "https://issues.apache.org/jira/rest/api/2/project/12319525",
            "id": "12319525",
            "key": "ARROW",
            "name": "Apache Arrow",
            "projectTypeKey": "software",
            "avatarUrls": {
                "48x48": "https://issues.apache.org/jira/secure/projectavatar?pid=12319525&avatarId=10011",
                "24x24": "https://issues.apache.org/jira/secure/projectavatar?size=small&pid=12319525&avatarId=10011",
                "16x16": "https://issues.apache.org/jira/secure/projectavatar?size=xsmall&pid=12319525&avatarId=10011",
                "32x32": "https://issues.apache.org/jira/secure/projectavatar?size=medium&pid=12319525&avatarId=10011"
            },
            "projectCategory": {
                "self": "https://issues.apache.org/jira/rest/api/2/projectCategory/13960",
                "id": "13960",
                "description": "Apache Arrow",
                "name": "Arrow"
            }
        },
        "aggregatetimespent": 4800,
        "customfield_12312520": null,
        "customfield_12312521": "Thu Feb 03 03:48:38 UTC 2022",
        "customfield_12314422": null,
        "customfield_12314421": null,
        "customfield_12314146": null,
        "customfield_12314420": null,
        "customfield_12314145": null,
        "customfield_12314144": null,
        "customfield_12314143": null,
        "resolutiondate": "2022-02-03T03:48:38.000+0000",
        "workratio": -1,
        "customfield_12312923": null,
        "customfield_12312920": null,
        "customfield_12312921": null,
        "watches": {
            "self": "https://issues.apache.org/jira/rest/api/2/issue/ARROW-15539/watchers",
            "watchCount": 1,
            "isWatching": false
        },
        "created": "2022-02-03T00:38:47.000+0000",
        "updated": "2022-02-04T03:11:45.000+0000",
        "timeoriginalestimate": null,
        "description": "Steps to reproduce:\r\n\r\n\u00a0\r\n{code:java}\r\n$ export ARROW_JEMALLOC=OFF\r\n$ archery benchmark run --repetitions 1\u00a0\r\n-- Building using CMake version: 3.21.3\r\n-- The C compiler identification is Clang 11.1.0\r\n-- The CXX compiler identification is Clang 11.1.0\r\n-- Detecting C compiler ABI info\r\n-- Detecting C compiler ABI info - done\r\n-- Check for working C compiler: /Users/voltrondata/miniconda3/envs/arrow-commit/bin/arm64-apple-darwin20.0.0-clang - skipped\r\n-- Detecting C compile features\r\n-- Detecting C compile features - done\r\n-- Detecting CXX compiler ABI info\r\n-- Detecting CXX compiler ABI info - done\r\n-- Check for working CXX compiler: /Users/voltrondata/miniconda3/envs/arrow-commit/bin/arm64-apple-darwin20.0.0-clang++ - skipped\r\n-- Detecting CXX compile features\r\n-- Detecting CXX compile features - done\r\n-- Arrow version: 7.0.0 (full: '7.0.0-SNAPSHOT')\r\n-- Arrow SO version: 700 (full: 700.0.0)\r\n-- clang-tidy 12 not found\r\n-- clang-format 12 not found\r\n-- Could NOT find ClangTools (missing: CLANG_FORMAT_BIN CLANG_TIDY_BIN)\u00a0\r\n-- infer not found\r\n-- Found Python3: /Users/voltrondata/miniconda3/envs/arrow-commit/bin/python3.8 (found version \"3.8.12\") found components: Interpreter\u00a0\r\n-- Using ccache: /Users/voltrondata/miniconda3/envs/arrow-commit/bin/ccache\r\n-- Found cpplint executable at /opt/homebrew/var/buildkite-agent/builds/test-mac-arm/apache-arrow/arrow-bci-benchmark-on-test-mac-arm/arrow/cpp/build-support/cpplint.py\r\n-- System processor: arm64\r\n-- Performing Test CXX_SUPPORTS_ARMV8_ARCH\r\n-- Performing Test CXX_SUPPORTS_ARMV8_ARCH - Success\r\n-- Arrow build warning level: PRODUCTION\r\nConfigured for RELEASE build (set with cmake -DCMAKE_BUILD_TYPE={release,debug,...})\r\n-- Build Type: RELEASE\r\n-- Performing Test CXX_LINKER_SUPPORTS_VERSION_SCRIPT\r\n-- Performing Test CXX_LINKER_SUPPORTS_VERSION_SCRIPT - Failed\r\n-- Using CONDA approach to find dependencies\r\n-- Using CONDA_PREFIX for ARROW_PACKAGE_PREFIX: /Users/voltrondata/miniconda3/envs/arrow-commit\r\n-- Setting (unset) dependency *_ROOT variables: /Users/voltrondata/miniconda3/envs/arrow-commit\r\n-- ARROW_ABSL_BUILD_VERSION: 20210324.2\r\n-- ARROW_ABSL_BUILD_SHA256_CHECKSUM: 59b862f50e710277f8ede96f083a5bb8d7c9595376146838b9580be90374ee1f\r\n-- ARROW_AWSSDK_BUILD_VERSION: 1.8.133\r\n-- ARROW_AWSSDK_BUILD_SHA256_CHECKSUM: d6c495bc06be5e21dac716571305d77437e7cfd62a2226b8fe48d9ab5785a8d6\r\n-- ARROW_AWS_CHECKSUMS_BUILD_VERSION: v0.1.12\r\n-- ARROW_AWS_CHECKSUMS_BUILD_SHA256_CHECKSUM: 394723034b81cc7cd528401775bc7aca2b12c7471c92350c80a0e2fb9d2909fe\r\n-- ARROW_AWS_C_COMMON_BUILD_VERSION: v0.6.9\r\n-- ARROW_AWS_C_COMMON_BUILD_SHA256_CHECKSUM: 928a3e36f24d1ee46f9eec360ec5cebfe8b9b8994fe39d4fa74ff51aebb12717\r\n-- ARROW_AWS_C_EVENT_STREAM_BUILD_VERSION: v0.1.5\r\n-- ARROW_AWS_C_EVENT_STREAM_BUILD_SHA256_CHECKSUM: f1b423a487b5d6dca118bfc0d0c6cc596dc476b282258a3228e73a8f730422d4\r\n-- ARROW_BOOST_BUILD_VERSION: 1.75.0\r\n-- ARROW_BOOST_BUILD_SHA256_CHECKSUM: 267e04a7c0bfe85daf796dedc789c3a27a76707e1c968f0a2a87bb96331e2b61\r\n-- ARROW_BROTLI_BUILD_VERSION: v1.0.9\r\n-- ARROW_BROTLI_BUILD_SHA256_CHECKSUM: f9e8d81d0405ba66d181529af42a3354f838c939095ff99930da6aa9cdf6fe46\r\n-- ARROW_BZIP2_BUILD_VERSION: 1.0.8\r\n-- ARROW_BZIP2_BUILD_SHA256_CHECKSUM: ab5a03176ee106d3f0fa90e381da478ddae405918153cca248e682cd0c4a2269\r\n-- ARROW_CARES_BUILD_VERSION: 1.17.2\r\n-- ARROW_CARES_BUILD_SHA256_CHECKSUM: 4803c844ce20ce510ef0eb83f8ea41fa24ecaae9d280c468c582d2bb25b3913d\r\n-- ARROW_CRC32C_BUILD_VERSION: 1.1.2\r\n-- ARROW_CRC32C_BUILD_SHA256_CHECKSUM: ac07840513072b7fcebda6e821068aa04889018f24e10e46181068fb214d7e56\r\n-- ARROW_GBENCHMARK_BUILD_VERSION: v1.6.0\r\n-- ARROW_GBENCHMARK_BUILD_SHA256_CHECKSUM: 1f71c72ce08d2c1310011ea6436b31e39ccab8c2db94186d26657d41747c85d6\r\n-- ARROW_GFLAGS_BUILD_VERSION: v2.2.2\r\n-- ARROW_GFLAGS_BUILD_SHA256_CHECKSUM: 34af2f15cf7367513b352bdcd2493ab14ce43692d2dcd9dfc499492966c64dcf\r\n-- ARROW_GLOG_BUILD_VERSION: v0.5.0\r\n-- ARROW_GLOG_BUILD_SHA256_CHECKSUM: eede71f28371bf39aa69b45de23b329d37214016e2055269b3b5e7cfd40b59f5\r\n-- ARROW_GOOGLE_CLOUD_CPP_BUILD_VERSION: v1.31.1\r\n-- ARROW_GOOGLE_CLOUD_CPP_BUILD_SHA256_CHECKSUM: dc7cbf95b506a84b48cf71e0462985d262183edeaabdacaaee2109852394a609\r\n-- ARROW_GRPC_BUILD_VERSION: v1.35.0\r\n-- ARROW_GRPC_BUILD_SHA256_CHECKSUM: 27dd2fc5c9809ddcde8eb6fa1fa278a3486566dfc28335fca13eb8df8bd3b958\r\n-- ARROW_GTEST_BUILD_VERSION: 1.11.0\r\n-- ARROW_GTEST_BUILD_SHA256_CHECKSUM: b4870bf121ff7795ba20d20bcdd8627b8e088f2d1dab299a031c1034eddc93d5\r\n-- ARROW_JEMALLOC_BUILD_VERSION: 5.2.1\r\n-- ARROW_JEMALLOC_BUILD_SHA256_CHECKSUM: 34330e5ce276099e2e8950d9335db5a875689a4c6a56751ef3b1d8c537f887f6\r\n-- ARROW_LZ4_BUILD_VERSION: 8f61d8eb7c6979769a484cde8df61ff7c4c77765\r\n-- ARROW_LZ4_BUILD_SHA256_CHECKSUM: 5b072d848f2f93fddb97e1143e22c1bd7fa19fc8431ee69e21758190a88125b4\r\n-- ARROW_MIMALLOC_BUILD_VERSION: v1.7.3\r\n-- ARROW_MIMALLOC_BUILD_SHA256_CHECKSUM: 0f987bda01ca9df87ec90e9d98c63fa893ee61f3cca565e5ca5ed744fdcc5109\r\n-- ARROW_NLOHMANN_JSON_BUILD_VERSION: v3.10.2\r\n-- ARROW_NLOHMANN_JSON_BUILD_SHA256_CHECKSUM: 081ed0f9f89805c2d96335c3acfa993b39a0a5b4b4cef7edb68dd2210a13458c\r\n-- ARROW_OPENTELEMETRY_BUILD_VERSION: v1.1.0\r\n-- ARROW_OPENTELEMETRY_BUILD_SHA256_CHECKSUM: f8fd3adddd47be382dc79c19d7e7efcf86a0dfbb5a237db6e0618dbb7eb8e058\r\n-- ARROW_OPENTELEMETRY_PROTO_BUILD_VERSION: v0.11.0\r\n-- ARROW_OPENTELEMETRY_PROTO_BUILD_SHA256_CHECKSUM: 985367f8905e91018e636cbf0d83ab3f834b665c4f5899a27d10cae9657710e2\r\n-- ARROW_ORC_BUILD_VERSION: 1.7.2\r\n-- ARROW_ORC_BUILD_SHA256_CHECKSUM: ef39bae755116fecb07fb4334656f984ba8ce7cdb1c64de078d3ed186b286007\r\n-- ARROW_PROTOBUF_BUILD_VERSION: v3.18.1\r\n-- ARROW_PROTOBUF_BUILD_SHA256_CHECKSUM: b8ab9bbdf0c6968cf20060794bc61e231fae82aaf69d6e3577c154181991f576\r\n-- ARROW_RAPIDJSON_BUILD_VERSION: 1a803826f1197b5e30703afe4b9c0e7dd48074f5\r\n-- ARROW_RAPIDJSON_BUILD_SHA256_CHECKSUM: 0b6b780b6c534bfb0b23d29910bfe361e486bcfeaf106db8bc8995792072905a\r\n-- ARROW_RE2_BUILD_VERSION: 2021-11-01\r\n-- ARROW_RE2_BUILD_SHA256_CHECKSUM: 8c45f7fba029ab41f2a7e6545058d9eec94eef97ce70df58e92d85cfc08b4669\r\n-- ARROW_SNAPPY_BUILD_VERSION: 1.1.9\r\n-- ARROW_SNAPPY_BUILD_SHA256_CHECKSUM: 75c1fbb3d618dd3a0483bff0e26d0a92b495bbe5059c8b4f1c962b478b6e06e7\r\n-- ARROW_SNAPPY_OLD_BUILD_VERSION: 1.1.8\r\n-- ARROW_SNAPPY_OLD_BUILD_SHA256_CHECKSUM: 16b677f07832a612b0836178db7f374e414f94657c138e6993cbfc5dcc58651f\r\n-- ARROW_THRIFT_BUILD_VERSION: 0.13.0\r\n-- ARROW_THRIFT_BUILD_SHA256_CHECKSUM: 7ad348b88033af46ce49148097afe354d513c1fca7c607b59c33ebb6064b5179\r\n-- ARROW_UTF8PROC_BUILD_VERSION: v2.7.0\r\n-- ARROW_UTF8PROC_BUILD_SHA256_CHECKSUM: 4bb121e297293c0fd55f08f83afab6d35d48f0af4ecc07523ad8ec99aa2b12a1\r\n-- ARROW_XSIMD_BUILD_VERSION: aeec9c872c8b475dedd7781336710f2dd2666cb2\r\n-- ARROW_XSIMD_BUILD_SHA256_CHECKSUM: 0a841e6c8acf216150e4fc19fca8e29fbab9614b56ac7b96e56019264ca27b26\r\n-- ARROW_ZLIB_BUILD_VERSION: 1.2.11\r\n-- ARROW_ZLIB_BUILD_SHA256_CHECKSUM: c3e5e9fdd5004dcb542feda5ee4f0ff0744628baf8ed2dd5d66f8ca1197cb1a1\r\n-- ARROW_ZSTD_BUILD_VERSION: v1.5.1\r\n-- ARROW_ZSTD_BUILD_SHA256_CHECKSUM: dc05773342b28f11658604381afd22cb0a13e8ba17ff2bd7516df377060c18dd\r\n-- Looking for pthread.h\r\n-- Looking for pthread.h - found\r\n-- Performing Test CMAKE_HAVE_LIBC_PTHREAD\r\n-- Performing Test CMAKE_HAVE_LIBC_PTHREAD - Success\r\n-- Found Threads: TRUE \u00a0\r\n-- Looking for _M_ARM64\r\n-- Looking for _M_ARM64 - not found\r\n-- Looking for __SIZEOF_INT128__\r\n-- Looking for __SIZEOF_INT128__ - found\r\n-- Found Boost: /Users/voltrondata/miniconda3/envs/arrow-commit/lib/cmake/Boost-1.77.0/BoostConfig.cmake (found suitable version \"1.77.0\", minimum required is \"1.58\") found components: system filesystem\u00a0\r\n-- Boost include dir: /Users/voltrondata/miniconda3/envs/arrow-commit/include\r\n-- Boost libraries: Boost::system;Boost::filesystem\r\n-- Found Snappy: /Users/voltrondata/miniconda3/envs/arrow-commit/lib/libsnappy.dylib \u00a0\r\n-- Providing CMake module for Snappy\r\n-- Checking for modules 'libbrotlicommon;libbrotlienc;libbrotlidec'\r\n-- \u00a0 Found libbrotlicommon, version 1.0.9\r\n-- \u00a0 Found libbrotlienc, version 1.0.9\r\n-- \u00a0 Found libbrotlidec, version 1.0.9\r\n-- Found Brotli: /Users/voltrondata/miniconda3/envs/arrow-commit/lib/libbrotlicommon.dylib \u00a0\r\n-- Providing CMake module for Brotli\r\n-- Building without OpenSSL support. Minimum OpenSSL version 1.0.2 required.\r\n-- Found Thrift: /Users/voltrondata/miniconda3/envs/arrow-commit/lib/libthrift.dylib (found suitable version \"0.15.0\", minimum required is \"0.11.0\") \u00a0\r\n-- Providing CMake module for Thrift\r\n-- Building (vendored) jemalloc from source\r\n-- RapidJSON found. Headers: /Users/voltrondata/miniconda3/envs/arrow-commit/include\r\n-- Building xsimd from source\r\n-- Found ZLIB: /Users/voltrondata/miniconda3/envs/arrow-commit/lib/libz.dylib (found version \"1.2.11\")\u00a0\r\n-- Checking for module 'liblz4'\r\n-- \u00a0 Found liblz4, version 1.9.3\r\n-- Found Lz4: /Users/voltrondata/miniconda3/envs/arrow-commit/lib/liblz4.dylib \u00a0\r\n-- Providing CMake module for Lz4\r\n-- Checking for module 'libzstd'\r\n-- \u00a0 Found libzstd, version 1.5.2\r\n-- Found zstd: /Users/voltrondata/miniconda3/envs/arrow-commit/lib/libzstd.dylib (Required is at least version \"1.4.0\")\u00a0\r\n-- Providing CMake module for zstd\r\n-- Providing CMake module for re2Alt\r\n-- Found BZip2: /Users/voltrondata/miniconda3/envs/arrow-commit/lib/libbz2.dylib (found version \"1.0.8\")\u00a0\r\n-- Looking for BZ2_bzCompressInit\r\n-- Looking for BZ2_bzCompressInit - found\r\n-- Found utf8proc: /Users/voltrondata/miniconda3/envs/arrow-commit/lib/libutf8proc.dylib (found suitable version \"2.7.0\", minimum required is \"2.2.0\")\u00a0\r\n-- Providing CMake module for utf8proc\r\n-- Found hdfs.h at: /opt/homebrew/var/buildkite-agent/builds/test-mac-arm/apache-arrow/arrow-bci-benchmark-on-test-mac-arm/arrow/cpp/thirdparty/hadoop/include/hdfs.h\r\n-- All bundled static libraries: jemalloc::jemalloc\r\n-- CMAKE_C_FLAGS: -ftree-vectorize -fPIC -fPIE -fstack-protector-strong -O2 -pipe -isystem /Users/voltrondata/miniconda3/envs/arrow-commit/include -Qunused-arguments -O3 -DNDEBUG \u00a0-Wall -Wno-unknown-warning-option -Wno-pass-failed -march=armv8-a\u00a0\r\n-- CMAKE_CXX_FLAGS: \u00a0-ftree-vectorize -fPIC -fPIE -fstack-protector-strong -O2 -pipe -stdlib=libc++ -fvisibility-inlines-hidden -std=c++14 -fmessage-length=0 -isystem /Users/voltrondata/miniconda3/envs/arrow-commit/include -Qunused-arguments -fcolor-diagnostics -O3 -DNDEBUG \u00a0-Wall -Wno-unknown-warning-option -Wno-pass-failed -march=armv8-a\u00a0\r\n-- Looking for backtrace\r\n-- Looking for backtrace - found\r\n-- backtrace facility detected in default set of libraries\r\n-- Found Backtrace: /Library/Developer/CommandLineTools/SDKs/MacOSX.sdk/usr/include \u00a0\r\n-- ---------------------------------------------------------------------\r\n-- Arrow version: \u00a0 \u00a0 \u00a0 \u00a0 \u00a0 \u00a0 \u00a0 \u00a0 \u00a0 \u00a0 \u00a0 \u00a0 \u00a0 \u00a0 \u00a0 \u00a0 7.0.0-SNAPSHOT\r\n--\u00a0\r\n-- Build configuration summary:\r\n-- \u00a0 Generator: Ninja\r\n-- \u00a0 Build type: RELEASE\r\n-- \u00a0 Source directory: /opt/homebrew/var/buildkite-agent/builds/test-mac-arm/apache-arrow/arrow-bci-benchmark-on-test-mac-arm/arrow/cpp\r\n-- \u00a0 Install prefix: /Users/voltrondata/miniconda3/envs/arrow-commit\r\n-- \u00a0 Compile commands: /private/var/folders/d9/n0lbzbf16nvgt7b83xhcssm80000gn/T/arrow-archery-69dlw34c/WORKSPACE/build/compile_commands.json\r\n--\u00a0\r\n-- Compile and link options:\r\n--\u00a0\r\n-- \u00a0 ARROW_CXXFLAGS=\"\" [default=\"\"]\r\n-- \u00a0 \u00a0 \u00a0 Compiler flags to append when compiling Arrow\r\n-- \u00a0 ARROW_BUILD_STATIC=OFF [default=ON]\r\n-- \u00a0 \u00a0 \u00a0 Build static libraries\r\n-- \u00a0 ARROW_BUILD_SHARED=ON [default=ON]\r\n-- \u00a0 \u00a0 \u00a0 Build shared libraries\r\n-- \u00a0 ARROW_PACKAGE_KIND=\"\" [default=\"\"]\r\n-- \u00a0 \u00a0 \u00a0 Arbitrary string that identifies the kind of package\r\n-- \u00a0 \u00a0 \u00a0 (for informational purposes)\r\n-- \u00a0 ARROW_GIT_ID=daa5c18e9697a6455a7a75fec19594543c17b21e [default=\"\"]\r\n-- \u00a0 \u00a0 \u00a0 The Arrow git commit id (if any)\r\n-- \u00a0 ARROW_GIT_DESCRIPTION=apache-arrow-7.0.0.dev-572-gdaa5c18e9 [default=\"\"]\r\n-- \u00a0 \u00a0 \u00a0 The Arrow git commit description (if any)\r\n-- \u00a0 ARROW_NO_DEPRECATED_API=OFF [default=OFF]\r\n-- \u00a0 \u00a0 \u00a0 Exclude deprecated APIs from build\r\n-- \u00a0 ARROW_USE_CCACHE=ON [default=ON]\r\n-- \u00a0 \u00a0 \u00a0 Use ccache when compiling (if available)\r\n-- \u00a0 ARROW_USE_LD_GOLD=ON [default=OFF]\r\n-- \u00a0 \u00a0 \u00a0 Use ld.gold for linking on Linux (if available)\r\n-- \u00a0 ARROW_USE_PRECOMPILED_HEADERS=OFF [default=OFF]\r\n-- \u00a0 \u00a0 \u00a0 Use precompiled headers when compiling\r\n-- \u00a0 ARROW_SIMD_LEVEL=NEON [default=NONE|SSE4_2|AVX2|AVX512|NEON|DEFAULT]\r\n-- \u00a0 \u00a0 \u00a0 Compile-time SIMD optimization level\r\n-- \u00a0 ARROW_RUNTIME_SIMD_LEVEL=MAX [default=NONE|SSE4_2|AVX2|AVX512|MAX]\r\n-- \u00a0 \u00a0 \u00a0 Max runtime SIMD optimization level\r\n-- \u00a0 ARROW_ARMV8_ARCH=armv8-a [default=armv8-a|armv8-a+crc+crypto]\r\n-- \u00a0 \u00a0 \u00a0 Arm64 arch and extensions\r\n-- \u00a0 ARROW_ALTIVEC=ON [default=ON]\r\n-- \u00a0 \u00a0 \u00a0 Build with Altivec if compiler has support\r\n-- \u00a0 ARROW_RPATH_ORIGIN=OFF [default=OFF]\r\n-- \u00a0 \u00a0 \u00a0 Build Arrow libraries with RATH set to $ORIGIN\r\n-- \u00a0 ARROW_INSTALL_NAME_RPATH=ON [default=ON]\r\n-- \u00a0 \u00a0 \u00a0 Build Arrow libraries with install_name set to @rpath\r\n-- \u00a0 ARROW_GGDB_DEBUG=ON [default=ON]\r\n-- \u00a0 \u00a0 \u00a0 Pass -ggdb flag to debug builds\r\n--\u00a0\r\n-- Test and benchmark options:\r\n--\u00a0\r\n-- \u00a0 ARROW_BUILD_EXAMPLES=OFF [default=OFF]\r\n-- \u00a0 \u00a0 \u00a0 Build the Arrow examples\r\n-- \u00a0 ARROW_BUILD_TESTS=OFF [default=OFF]\r\n-- \u00a0 \u00a0 \u00a0 Build the Arrow googletest unit tests\r\n-- \u00a0 ARROW_ENABLE_TIMING_TESTS=ON [default=ON]\r\n-- \u00a0 \u00a0 \u00a0 Enable timing-sensitive tests\r\n-- \u00a0 ARROW_BUILD_INTEGRATION=OFF [default=OFF]\r\n-- \u00a0 \u00a0 \u00a0 Build the Arrow integration test executables\r\n-- \u00a0 ARROW_BUILD_BENCHMARKS=ON [default=OFF]\r\n-- \u00a0 \u00a0 \u00a0 Build the Arrow micro benchmarks\r\n-- \u00a0 ARROW_BUILD_BENCHMARKS_REFERENCE=OFF [default=OFF]\r\n-- \u00a0 \u00a0 \u00a0 Build the Arrow micro reference benchmarks\r\n-- \u00a0 ARROW_BUILD_OPENMP_BENCHMARKS=OFF [default=OFF]\r\n-- \u00a0 \u00a0 \u00a0 Build the Arrow benchmarks that rely on OpenMP\r\n-- \u00a0 ARROW_BUILD_DETAILED_BENCHMARKS=OFF [default=OFF]\r\n-- \u00a0 \u00a0 \u00a0 Build benchmarks that do a longer exploration of performance\r\n-- \u00a0 ARROW_TEST_LINKAGE=shared [default=shared|static]\r\n-- \u00a0 \u00a0 \u00a0 Linkage of Arrow libraries with unit tests executables.\r\n-- \u00a0 ARROW_FUZZING=OFF [default=OFF]\r\n-- \u00a0 \u00a0 \u00a0 Build Arrow Fuzzing executables\r\n-- \u00a0 ARROW_LARGE_MEMORY_TESTS=OFF [default=OFF]\r\n-- \u00a0 \u00a0 \u00a0 Enable unit tests which use large memory\r\n--\u00a0\r\n-- Lint options:\r\n--\u00a0\r\n-- \u00a0 ARROW_ONLY_LINT=OFF [default=OFF]\r\n-- \u00a0 \u00a0 \u00a0 Only define the lint and check-format targets\r\n-- \u00a0 ARROW_VERBOSE_LINT=OFF [default=OFF]\r\n-- \u00a0 \u00a0 \u00a0 If off, 'quiet' flags will be passed to linting tools\r\n-- \u00a0 ARROW_GENERATE_COVERAGE=OFF [default=OFF]\r\n-- \u00a0 \u00a0 \u00a0 Build with C++ code coverage enabled\r\n--\u00a0\r\n-- Checks options:\r\n--\u00a0\r\n-- \u00a0 ARROW_TEST_MEMCHECK=OFF [default=OFF]\r\n-- \u00a0 \u00a0 \u00a0 Run the test suite using valgrind --tool=memcheck\r\n-- \u00a0 ARROW_USE_ASAN=OFF [default=OFF]\r\n-- \u00a0 \u00a0 \u00a0 Enable Address Sanitizer checks\r\n-- \u00a0 ARROW_USE_TSAN=OFF [default=OFF]\r\n-- \u00a0 \u00a0 \u00a0 Enable Thread Sanitizer checks\r\n-- \u00a0 ARROW_USE_UBSAN=OFF [default=OFF]\r\n-- \u00a0 \u00a0 \u00a0 Enable Undefined Behavior sanitizer checks\r\n--\u00a0\r\n-- Project component options:\r\n--\u00a0\r\n-- \u00a0 ARROW_BUILD_UTILITIES=OFF [default=OFF]\r\n-- \u00a0 \u00a0 \u00a0 Build Arrow commandline utilities\r\n-- \u00a0 ARROW_COMPUTE=ON [default=OFF]\r\n-- \u00a0 \u00a0 \u00a0 Build the Arrow Compute Modules\r\n-- \u00a0 ARROW_CSV=ON [default=OFF]\r\n-- \u00a0 \u00a0 \u00a0 Build the Arrow CSV Parser Module\r\n-- \u00a0 ARROW_CUDA=OFF [default=OFF]\r\n-- \u00a0 \u00a0 \u00a0 Build the Arrow CUDA extensions (requires CUDA toolkit)\r\n-- \u00a0 ARROW_DATASET=ON [default=OFF]\r\n-- \u00a0 \u00a0 \u00a0 Build the Arrow Dataset Modules\r\n-- \u00a0 ARROW_ENGINE=OFF [default=OFF]\r\n-- \u00a0 \u00a0 \u00a0 Build the Arrow Execution Engine\r\n-- \u00a0 ARROW_FILESYSTEM=ON [default=OFF]\r\n-- \u00a0 \u00a0 \u00a0 Build the Arrow Filesystem Layer\r\n-- \u00a0 ARROW_FLIGHT=OFF [default=OFF]\r\n-- \u00a0 \u00a0 \u00a0 Build the Arrow Flight RPC System (requires GRPC, Protocol Buffers)\r\n-- \u00a0 ARROW_FLIGHT_SQL=OFF [default=OFF]\r\n-- \u00a0 \u00a0 \u00a0 Build the Arrow Flight SQL extension\r\n-- \u00a0 ARROW_GANDIVA=OFF [default=OFF]\r\n-- \u00a0 \u00a0 \u00a0 Build the Gandiva libraries\r\n-- \u00a0 ARROW_GCS=OFF [default=OFF]\r\n-- \u00a0 \u00a0 \u00a0 Build Arrow with GCS support (requires the GCloud SDK for C++)\r\n-- \u00a0 ARROW_HDFS=OFF [default=OFF]\r\n-- \u00a0 \u00a0 \u00a0 Build the Arrow HDFS bridge\r\n-- \u00a0 ARROW_HIVESERVER2=OFF [default=OFF]\r\n-- \u00a0 \u00a0 \u00a0 Build the HiveServer2 client and Arrow adapter\r\n-- \u00a0 ARROW_IPC=ON [default=ON]\r\n-- \u00a0 \u00a0 \u00a0 Build the Arrow IPC extensions\r\n-- \u00a0 ARROW_JEMALLOC=ON [default=ON]\r\n-- \u00a0 \u00a0 \u00a0 Build the Arrow jemalloc-based allocator\r\n-- \u00a0 ARROW_JNI=OFF [default=OFF]\r\n-- \u00a0 \u00a0 \u00a0 Build the Arrow JNI lib\r\n-- \u00a0 ARROW_JSON=ON [default=OFF]\r\n-- \u00a0 \u00a0 \u00a0 Build Arrow with JSON support (requires RapidJSON)\r\n-- \u00a0 ARROW_MIMALLOC=OFF [default=OFF]\r\n-- \u00a0 \u00a0 \u00a0 Build the Arrow mimalloc-based allocator\r\n-- \u00a0 ARROW_PARQUET=ON [default=OFF]\r\n-- \u00a0 \u00a0 \u00a0 Build the Parquet libraries\r\n-- \u00a0 ARROW_ORC=OFF [default=OFF]\r\n-- \u00a0 \u00a0 \u00a0 Build the Arrow ORC adapter\r\n-- \u00a0 ARROW_PLASMA=OFF [default=OFF]\r\n-- \u00a0 \u00a0 \u00a0 Build the plasma object store along with Arrow\r\n-- \u00a0 ARROW_PLASMA_JAVA_CLIENT=OFF [default=OFF]\r\n-- \u00a0 \u00a0 \u00a0 Build the plasma object store java client\r\n-- \u00a0 ARROW_PYTHON=OFF [default=OFF]\r\n-- \u00a0 \u00a0 \u00a0 Build the Arrow CPython extensions\r\n-- \u00a0 ARROW_S3=OFF [default=OFF]\r\n-- \u00a0 \u00a0 \u00a0 Build Arrow with S3 support (requires the AWS SDK for C++)\r\n-- \u00a0 ARROW_SKYHOOK=OFF [default=OFF]\r\n-- \u00a0 \u00a0 \u00a0 Build the Skyhook libraries\r\n-- \u00a0 ARROW_TENSORFLOW=OFF [default=OFF]\r\n-- \u00a0 \u00a0 \u00a0 Build Arrow with TensorFlow support enabled\r\n-- \u00a0 ARROW_TESTING=ON [default=OFF]\r\n-- \u00a0 \u00a0 \u00a0 Build the Arrow testing libraries\r\n--\u00a0\r\n-- Thirdparty toolchain options:\r\n--\u00a0\r\n-- \u00a0 ARROW_DEPENDENCY_SOURCE=CONDA [default=AUTO|BUNDLED|SYSTEM|CONDA|VCPKG|BREW]\r\n-- \u00a0 \u00a0 \u00a0 Method to use for acquiring arrow's build dependencies\r\n-- \u00a0 ARROW_VERBOSE_THIRDPARTY_BUILD=OFF [default=OFF]\r\n-- \u00a0 \u00a0 \u00a0 Show output from ExternalProjects rather than just logging to files\r\n-- \u00a0 ARROW_DEPENDENCY_USE_SHARED=ON [default=ON]\r\n-- \u00a0 \u00a0 \u00a0 Link to shared libraries\r\n-- \u00a0 ARROW_BOOST_USE_SHARED=ON [default=ON]\r\n-- \u00a0 \u00a0 \u00a0 Rely on boost shared libraries where relevant\r\n-- \u00a0 ARROW_BROTLI_USE_SHARED=ON [default=ON]\r\n-- \u00a0 \u00a0 \u00a0 Rely on Brotli shared libraries where relevant\r\n-- \u00a0 ARROW_BZ2_USE_SHARED=ON [default=ON]\r\n-- \u00a0 \u00a0 \u00a0 Rely on Bz2 shared libraries where relevant\r\n-- \u00a0 ARROW_GFLAGS_USE_SHARED=ON [default=ON]\r\n-- \u00a0 \u00a0 \u00a0 Rely on GFlags shared libraries where relevant\r\n-- \u00a0 ARROW_GRPC_USE_SHARED=ON [default=ON]\r\n-- \u00a0 \u00a0 \u00a0 Rely on gRPC shared libraries where relevant\r\n-- \u00a0 ARROW_LZ4_USE_SHARED=ON [default=ON]\r\n-- \u00a0 \u00a0 \u00a0 Rely on lz4 shared libraries where relevant\r\n-- \u00a0 ARROW_OPENSSL_USE_SHARED=ON [default=ON]\r\n-- \u00a0 \u00a0 \u00a0 Rely on OpenSSL shared libraries where relevant\r\n-- \u00a0 ARROW_PROTOBUF_USE_SHARED=ON [default=ON]\r\n-- \u00a0 \u00a0 \u00a0 Rely on Protocol Buffers shared libraries where relevant\r\n-- \u00a0 ARROW_THRIFT_USE_SHARED=ON [default=ON]\r\n-- \u00a0 \u00a0 \u00a0 Rely on thrift shared libraries where relevant\r\n-- \u00a0 ARROW_UTF8PROC_USE_SHARED=ON [default=ON]\r\n-- \u00a0 \u00a0 \u00a0 Rely on utf8proc shared libraries where relevant\r\n-- \u00a0 ARROW_SNAPPY_USE_SHARED=ON [default=ON]\r\n-- \u00a0 \u00a0 \u00a0 Rely on snappy shared libraries where relevant\r\n-- \u00a0 ARROW_UTF8PROC_USE_SHARED=ON [default=ON]\r\n-- \u00a0 \u00a0 \u00a0 Rely on utf8proc shared libraries where relevant\r\n-- \u00a0 ARROW_ZSTD_USE_SHARED=ON [default=ON]\r\n-- \u00a0 \u00a0 \u00a0 Rely on zstd shared libraries where relevant\r\n-- \u00a0 ARROW_USE_GLOG=OFF [default=OFF]\r\n-- \u00a0 \u00a0 \u00a0 Build libraries with glog support for pluggable logging\r\n-- \u00a0 ARROW_WITH_BACKTRACE=ON [default=ON]\r\n-- \u00a0 \u00a0 \u00a0 Build with backtrace support\r\n-- \u00a0 ARROW_WITH_OPENTELEMETRY=OFF [default=OFF]\r\n-- \u00a0 \u00a0 \u00a0 Build libraries with OpenTelemetry support for distributed tracing\r\n-- \u00a0 ARROW_WITH_BROTLI=ON [default=OFF]\r\n-- \u00a0 \u00a0 \u00a0 Build with Brotli compression\r\n-- \u00a0 ARROW_WITH_BZ2=ON [default=OFF]\r\n-- \u00a0 \u00a0 \u00a0 Build with BZ2 compression\r\n-- \u00a0 ARROW_WITH_LZ4=ON [default=OFF]\r\n-- \u00a0 \u00a0 \u00a0 Build with lz4 compression\r\n-- \u00a0 ARROW_WITH_SNAPPY=ON [default=OFF]\r\n-- \u00a0 \u00a0 \u00a0 Build with Snappy compression\r\n-- \u00a0 ARROW_WITH_ZLIB=ON [default=OFF]\r\n-- \u00a0 \u00a0 \u00a0 Build with zlib compression\r\n-- \u00a0 ARROW_WITH_ZSTD=ON [default=OFF]\r\n-- \u00a0 \u00a0 \u00a0 Build with zstd compression\r\n-- \u00a0 ARROW_WITH_UTF8PROC=ON [default=ON]\r\n-- \u00a0 \u00a0 \u00a0 Build with support for Unicode properties using the utf8proc library\r\n-- \u00a0 \u00a0 \u00a0 (only used if ARROW_COMPUTE is ON or ARROW_GANDIVA is ON)\r\n-- \u00a0 ARROW_WITH_RE2=ON [default=ON]\r\n-- \u00a0 \u00a0 \u00a0 Build with support for regular expressions using the re2 library\r\n-- \u00a0 \u00a0 \u00a0 (only used if ARROW_COMPUTE or ARROW_GANDIVA is ON)\r\n--\u00a0\r\n-- Parquet options:\r\n--\u00a0\r\n-- \u00a0 PARQUET_MINIMAL_DEPENDENCY=OFF [default=OFF]\r\n-- \u00a0 \u00a0 \u00a0 Depend only on Thirdparty headers to build libparquet.\r\n-- \u00a0 \u00a0 \u00a0 Always OFF if building binaries\r\n-- \u00a0 PARQUET_BUILD_EXECUTABLES=OFF [default=OFF]\r\n-- \u00a0 \u00a0 \u00a0 Build the Parquet executable CLI tools. Requires static libraries to be built.\r\n-- \u00a0 PARQUET_BUILD_EXAMPLES=OFF [default=OFF]\r\n-- \u00a0 \u00a0 \u00a0 Build the Parquet examples. Requires static libraries to be built.\r\n-- \u00a0 PARQUET_REQUIRE_ENCRYPTION=OFF [default=OFF]\r\n-- \u00a0 \u00a0 \u00a0 Build support for encryption. Fail if OpenSSL is not found\r\n--\u00a0\r\n-- Gandiva options:\r\n--\u00a0\r\n-- \u00a0 ARROW_GANDIVA_JAVA=OFF [default=OFF]\r\n-- \u00a0 \u00a0 \u00a0 Build the Gandiva JNI wrappers\r\n-- \u00a0 ARROW_GANDIVA_STATIC_LIBSTDCPP=OFF [default=OFF]\r\n-- \u00a0 \u00a0 \u00a0 Include -static-libstdc++ -static-libgcc when linking with\r\n-- \u00a0 \u00a0 \u00a0 Gandiva static libraries\r\n-- \u00a0 ARROW_GANDIVA_PC_CXX_FLAGS=\"\" [default=\"\"]\r\n-- \u00a0 \u00a0 \u00a0 Compiler flags to append when pre-compiling Gandiva operations\r\n--\u00a0\r\n-- Advanced developer options:\r\n--\u00a0\r\n-- \u00a0 ARROW_EXTRA_ERROR_CONTEXT=OFF [default=OFF]\r\n-- \u00a0 \u00a0 \u00a0 Compile with extra error context (line numbers, code)\r\n-- \u00a0 ARROW_OPTIONAL_INSTALL=OFF [default=OFF]\r\n-- \u00a0 \u00a0 \u00a0 If enabled install ONLY targets that have already been built. Please be\r\n-- \u00a0 \u00a0 \u00a0 advised that if this is enabled 'install' will fail silently on components\r\n-- \u00a0 \u00a0 \u00a0 that have not been built\r\n-- \u00a0 Outputting build configuration summary to /private/var/folders/d9/n0lbzbf16nvgt7b83xhcssm80000gn/T/arrow-archery-69dlw34c/WORKSPACE/build/cmake_summary.json\r\n-- Configuring done\r\n-- Generating done\r\n-- Build files have been written to: /private/var/folders/d9/n0lbzbf16nvgt7b83xhcssm80000gn/T/arrow-archery-69dlw34c/WORKSPACE/build\r\n[13/168] Performing configure step for 'jemalloc_ep'\r\nFAILED: jemalloc_ep-prefix/src/jemalloc_ep-stamp/jemalloc_ep-configure /private/var/folders/d9/n0lbzbf16nvgt7b83xhcssm80000gn/T/arrow-archery-69dlw34c/WORKSPACE/build/jemalloc_ep-prefix/src/jemalloc_ep-stamp/jemalloc_ep-configure\u00a0\r\ncd /private/var/folders/d9/n0lbzbf16nvgt7b83xhcssm80000gn/T/arrow-archery-69dlw34c/WORKSPACE/build/jemalloc_ep-prefix/src/jemalloc_ep && /Users/voltrondata/miniconda3/envs/arrow-commit/bin/cmake -P /private/var/folders/d9/n0lbzbf16nvgt7b83xhcssm80000gn/T/arrow-archery-69dlw34c/WORKSPACE/build/jemalloc_ep-prefix/src/jemalloc_ep-stamp/jemalloc_ep-configure-RELEASE.cmake && /Users/voltrondata/miniconda3/envs/arrow-commit/bin/cmake -E touch /private/var/folders/d9/n0lbzbf16nvgt7b83xhcssm80000gn/T/arrow-archery-69dlw34c/WORKSPACE/build/jemalloc_ep-prefix/src/jemalloc_ep-stamp/jemalloc_ep-configure\r\nCMake Error at /private/var/folders/d9/n0lbzbf16nvgt7b83xhcssm80000gn/T/arrow-archery-69dlw34c/WORKSPACE/build/jemalloc_ep-prefix/src/jemalloc_ep-stamp/jemalloc_ep-configure-RELEASE.cmake:37 (message):\r\n\u00a0 Command failed: 1\u00a0 \u00a0'./configure' 'AR=/Users/voltrondata/miniconda3/envs/arrow-commit/bin/arm64-apple-darwin20.0.0-ar' 'CC=/Users/voltrondata/miniconda3/envs/arrow-commit/bin/arm64-apple-darwin20.0.0-clang' 'SDKROOT=/Library/Developer/CommandLineTools/SDKs/MacOSX.sdk' '--prefix=/private/var/folders/d9/n0lbzbf16nvgt7b83xhcssm80000gn/T/arrow-archery-69dlw34c/WORKSPACE/build/jemalloc_ep-prefix/src/jemalloc_ep/dist/' '--libdir=/private/var/folders/d9/n0lbzbf16nvgt7b83xhcssm80000gn/T/arrow-archery-69dlw34c/WORKSPACE/build/jemalloc_ep-prefix/src/jemalloc_ep/dist//lib' '--with-jemalloc-prefix=je_arrow_' '--with-private-namespace=je_arrow_private_' '--without-export' '--disable-shared' '--disable-cxx' '--disable-libdl' '--disable-initial-exec-tls'\u00a0 See also\u00a0 \u00a0 /private/var/folders/d9/n0lbzbf16nvgt7b83xhcssm80000gn/T/arrow-archery-69dlw34c/WORKSPACE/build/jemalloc_ep-prefix/src/jemalloc_ep-stamp/jemalloc_ep-configure-*.log\r\n-- stdout output is:\r\nchecking for xsltproc... /usr/bin/xsltproc\r\nchecking for arm64-apple-darwin20.0.0-gcc... /Users/voltrondata/miniconda3/envs/arrow-commit/bin/arm64-apple-darwin20.0.0-clang\r\nchecking whether the C compiler works... yes\r\nchecking for C compiler default output file name... a.out\r\nchecking for suffix of executables...\u00a0\r\nchecking whether we are cross compiling... no\r\nchecking for suffix of object files... o\r\nchecking whether we are using the GNU C compiler... yes\r\nchecking whether /Users/voltrondata/miniconda3/envs/arrow-commit/bin/arm64-apple-darwin20.0.0-clang accepts -g... yes\r\nchecking for /Users/voltrondata/miniconda3/envs/arrow-commit/bin/arm64-apple-darwin20.0.0-clang option to accept ISO C89... none needed\r\nchecking whether compiler is cray... no\r\nchecking whether compiler supports -std=gnu11... yes\r\nchecking whether compiler supports -Wall... yes\r\nchecking whether compiler supports -Wextra... yes\r\nchecking whether compiler supports -Wshorten-64-to-32... yes\r\nchecking whether compiler supports -Wsign-compare... yes\r\nchecking whether compiler supports -Wundef... yes\r\nchecking whether compiler supports -Wno-format-zero-length... yes\r\nchecking whether compiler supports -pipe... yes\r\nchecking whether compiler supports -g3... yes\r\nchecking how to run the C preprocessor... /Users/voltrondata/miniconda3/envs/arrow-commit/bin/arm64-apple-darwin20.0.0-clang -E\r\nchecking for grep that handles long lines and -e... /usr/bin/grep\r\nchecking for egrep... /usr/bin/grep -E\r\nchecking for ANSI C header files... yes\r\nchecking for sys/types.h... yes\r\nchecking for sys/stat.h... yes\r\nchecking for stdlib.h... yes\r\nchecking for string.h... yes\r\nchecking for memory.h... yes\r\nchecking for strings.h... yes\r\nchecking for inttypes.h... yes\r\nchecking for stdint.h... yes\r\nchecking for unistd.h... yes\r\nchecking whether byte ordering is bigendian... no\r\nchecking size of void *... 8\r\nchecking size of int... 4\r\nchecking size of long... 8\r\nchecking size of long long... 8\r\nchecking size of intmax_t... 8\r\nchecking build system type...\u00a0\r\n-- stderr output is:\r\nInvalid configuration `arm64-apple-darwin20.0.0': machine `arm64-apple' not recognized\r\nconfigure: error: /bin/sh build-aux/config.sub arm64-apple-darwin20.0.0 failedCMake Error at /private/var/folders/d9/n0lbzbf16nvgt7b83xhcssm80000gn/T/arrow-archery-69dlw34c/WORKSPACE/build/jemalloc_ep-prefix/src/jemalloc_ep-stamp/jemalloc_ep-configure-RELEASE.cmake:47 (message):\r\n\u00a0 Stopping after outputting logs.\r\n[22/168] Building CXX object src/arrow/CMakeFiles/arrow_objlib.dir/Unity/unity_20_cxx.cxx.o\r\nninja: build stopped: subcommand failed.\r\nTraceback (most recent call last):\r\n\u00a0 File \"/Users/voltrondata/miniconda3/envs/arrow-commit/bin/archery\", line 33, in <module>\r\n\u00a0 \u00a0 sys.exit(load_entry_point('archery', 'console_scripts', 'archery')())\r\n\u00a0 File \"/Users/voltrondata/miniconda3/envs/arrow-commit/lib/python3.8/site-packages/click/core.py\", line 1128, in __call__\r\n\u00a0 \u00a0 return self.main(*args, **kwargs)\r\n\u00a0 File \"/Users/voltrondata/miniconda3/envs/arrow-commit/lib/python3.8/site-packages/click/core.py\", line 1053, in main\r\n\u00a0 \u00a0 rv = self.invoke(ctx)\r\n\u00a0 File \"/Users/voltrondata/miniconda3/envs/arrow-commit/lib/python3.8/site-packages/click/core.py\", line 1659, in invoke\r\n\u00a0 \u00a0 return _process_result(sub_ctx.command.invoke(sub_ctx))\r\n\u00a0 File \"/Users/voltrondata/miniconda3/envs/arrow-commit/lib/python3.8/site-packages/click/core.py\", line 1659, in invoke\r\n\u00a0 \u00a0 return _process_result(sub_ctx.command.invoke(sub_ctx))\r\n\u00a0 File \"/Users/voltrondata/miniconda3/envs/arrow-commit/lib/python3.8/site-packages/click/core.py\", line 1395, in invoke\r\n\u00a0 \u00a0 return ctx.invoke(self.callback, **ctx.params)\r\n\u00a0 File \"/Users/voltrondata/miniconda3/envs/arrow-commit/lib/python3.8/site-packages/click/core.py\", line 754, in invoke\r\n\u00a0 \u00a0 return __callback(*args, **kwargs)\r\n\u00a0 File \"/Users/voltrondata/miniconda3/envs/arrow-commit/lib/python3.8/site-packages/click/decorators.py\", line 26, in new_func\r\n\u00a0 \u00a0 return f(get_current_context(), *args, **kwargs)\r\n\u00a0 File \"/opt/homebrew/var/buildkite-agent/builds/test-mac-arm/apache-arrow/arrow-bci-benchmark-on-test-mac-arm/arrow/dev/archery/archery/cli.py\", line 500, in benchmark_run\r\n\u00a0 \u00a0 json_out = json.dumps(runner_base, cls=JsonEncoder)\r\n\u00a0 File \"/Users/voltrondata/miniconda3/envs/arrow-commit/lib/python3.8/json/__init__.py\", line 234, in dumps\r\n\u00a0 \u00a0 return cls(\r\n\u00a0 File \"/Users/voltrondata/miniconda3/envs/arrow-commit/lib/python3.8/json/encoder.py\", line 199, in encode\r\n\u00a0 \u00a0 chunks = self.iterencode(o, _one_shot=True)\r\n\u00a0 File \"/Users/voltrondata/miniconda3/envs/arrow-commit/lib/python3.8/json/encoder.py\", line 257, in iterencode\r\n\u00a0 \u00a0 return _iterencode(o, 0)\r\n\u00a0 File \"/opt/homebrew/var/buildkite-agent/builds/test-mac-arm/apache-arrow/arrow-bci-benchmark-on-test-mac-arm/arrow/dev/archery/archery/benchmark/codec.py\", line 35, in default\r\n\u00a0 \u00a0 return BenchmarkRunnerCodec.encode(o)\r\n\u00a0 File \"/opt/homebrew/var/buildkite-agent/builds/test-mac-arm/apache-arrow/arrow-bci-benchmark-on-test-mac-arm/arrow/dev/archery/archery/benchmark/codec.py\", line 79, in encode\r\n\u00a0 \u00a0 return {\"suites\": [BenchmarkSuiteCodec.encode(s) for s in br.suites]}\r\n\u00a0 File \"/opt/homebrew/var/buildkite-agent/builds/test-mac-arm/apache-arrow/arrow-bci-benchmark-on-test-mac-arm/arrow/dev/archery/archery/benchmark/codec.py\", line 79, in <listcomp>\r\n\u00a0 \u00a0 return {\"suites\": [BenchmarkSuiteCodec.encode(s) for s in br.suites]}\r\n\u00a0 File \"/opt/homebrew/var/buildkite-agent/builds/test-mac-arm/apache-arrow/arrow-bci-benchmark-on-test-mac-arm/arrow/dev/archery/archery/benchmark/runner.py\", line 169, in suites\r\n\u00a0 \u00a0 suite_and_binaries = self.suites_binaries\r\n\u00a0 File \"/opt/homebrew/var/buildkite-agent/builds/test-mac-arm/apache-arrow/arrow-bci-benchmark-on-test-mac-arm/arrow/dev/archery/archery/benchmark/runner.py\", line 138, in suites_binaries\r\n\u00a0 \u00a0 self.build()\r\n\u00a0 File \"/opt/homebrew/var/buildkite-agent/builds/test-mac-arm/apache-arrow/arrow-bci-benchmark-on-test-mac-arm/arrow/dev/archery/archery/utils/command.py\", line 89, in __call__\r\n\u00a0 \u00a0 return self.run(*argv, **kwargs)\r\n\u00a0 File \"/opt/homebrew/var/buildkite-agent/builds/test-mac-arm/apache-arrow/arrow-bci-benchmark-on-test-mac-arm/arrow/dev/archery/archery/utils/cmake.py\", line 160, in run\r\n\u00a0 \u00a0 return super().run(*cmake_args, *extra,\r\n\u00a0 File \"/opt/homebrew/var/buildkite-agent/builds/test-mac-arm/apache-arrow/arrow-bci-benchmark-on-test-mac-arm/arrow/dev/archery/archery/utils/command.py\", line 78, in run\r\n\u00a0 \u00a0 return subprocess.run(invocation, **kwargs)\r\n\u00a0 File \"/Users/voltrondata/miniconda3/envs/arrow-commit/lib/python3.8/subprocess.py\", line 516, in run\r\n\u00a0 \u00a0 raise CalledProcessError(retcode, process.args,\r\nsubprocess.CalledProcessError: Command '['cmake', '--build', '/var/folders/d9/n0lbzbf16nvgt7b83xhcssm80000gn/T/arrow-archery-69dlw34c/WORKSPACE/build', '--']' returned non-zero exit status 1.\r\n {code}\r\nActual Result: Arrow C++ is built with ARROW_JEMALLOC=ON (printed in the logs)\r\n\r\nExpected Result: Arrow C++ is built with ARROW_JEMALLOC=OFF\r\n\r\n\u00a0\r\n\r\nI need to be able to set ARROW_JEMALLOC=OFF to avoid the issue with jemalloc\u00a0 on mac arm64 (printed in the logs).\r\n\r\nJemalloc issue is fixed by [~uwe] in [https://github.com/jemalloc/jemalloc/pull/2012|https://github.com/jemalloc/jemalloc/pull/2012/files]\r\n\r\nArrow is using latest jemalloc release version = 5.2.1 (created in 2019) but jemalloc issue is fixed after last release.\r\n\r\n\u00a0",
        "customfield_10010": null,
        "timetracking": {
            "remainingEstimate": "0h",
            "timeSpent": "1h 20m",
            "remainingEstimateSeconds": 0,
            "timeSpentSeconds": 4800
        },
        "customfield_12314523": null,
        "customfield_12314127": null,
        "customfield_12314522": null,
        "customfield_12314126": null,
        "customfield_12314521": null,
        "customfield_12314125": null,
        "customfield_12314520": null,
        "customfield_12314124": null,
        "attachment": [],
        "customfield_12312340": null,
        "customfield_12314123": null,
        "customfield_12312341": null,
        "customfield_12312220": null,
        "customfield_12314122": null,
        "customfield_12314121": null,
        "customfield_12314120": null,
        "customfield_12314129": null,
        "customfield_12314524": null,
        "customfield_12314128": null,
        "summary": "[Archery] Add ARROW_JEMALLOC to build options",
        "customfield_12314130": null,
        "customfield_12310291": null,
        "customfield_12310290": null,
        "customfield_12314138": null,
        "customfield_12314137": null,
        "environment": null,
        "customfield_12314136": null,
        "customfield_12314135": null,
        "customfield_12311020": null,
        "customfield_12314134": null,
        "duedate": null,
        "customfield_12314132": null,
        "customfield_12314131": null,
        "comment": {
            "comments": [
                {
                    "self": "https://issues.apache.org/jira/rest/api/2/issue/13426296/comment/17486205",
                    "id": "17486205",
                    "author": {
                        "self": "https://issues.apache.org/jira/rest/api/2/user?username=jonkeane",
                        "name": "jonkeane",
                        "key": "jonkeane",
                        "avatarUrls": {
                            "48x48": "https://issues.apache.org/jira/secure/useravatar?avatarId=34057",
                            "24x24": "https://issues.apache.org/jira/secure/useravatar?size=small&avatarId=34057",
                            "16x16": "https://issues.apache.org/jira/secure/useravatar?size=xsmall&avatarId=34057",
                            "32x32": "https://issues.apache.org/jira/secure/useravatar?size=medium&avatarId=34057"
                        },
                        "displayName": "Jonathan Keane",
                        "active": true,
                        "timeZone": "Etc/UTC"
                    },
                    "body": "Issue resolved by pull request 12325\n[https://github.com/apache/arrow/pull/12325]",
                    "updateAuthor": {
                        "self": "https://issues.apache.org/jira/rest/api/2/user?username=jonkeane",
                        "name": "jonkeane",
                        "key": "jonkeane",
                        "avatarUrls": {
                            "48x48": "https://issues.apache.org/jira/secure/useravatar?avatarId=34057",
                            "24x24": "https://issues.apache.org/jira/secure/useravatar?size=small&avatarId=34057",
                            "16x16": "https://issues.apache.org/jira/secure/useravatar?size=xsmall&avatarId=34057",
                            "32x32": "https://issues.apache.org/jira/secure/useravatar?size=medium&avatarId=34057"
                        },
                        "displayName": "Jonathan Keane",
                        "active": true,
                        "timeZone": "Etc/UTC"
                    },
                    "created": "2022-02-03T03:48:38.197+0000",
                    "updated": "2022-02-03T03:48:38.197+0000"
                }
            ],
            "maxResults": 1,
            "total": 1,
            "startAt": 0
        },
        "customfield_12311820": "0|z0z7ds:",
        "customfield_12314139": null
    }
}