{
    "expand": "operations,versionedRepresentations,editmeta,changelog,renderedFields",
    "id": "13219199",
    "self": "https://issues.apache.org/jira/rest/api/2/issue/13219199",
    "key": "ARROW-4752",
    "fields": {
        "fixVersions": [
            {
                "self": "https://issues.apache.org/jira/rest/api/2/version/12345978",
                "id": "12345978",
                "description": "",
                "name": "0.15.0",
                "archived": false,
                "released": true,
                "releaseDate": "2019-10-05"
            }
        ],
        "resolution": {
            "self": "https://issues.apache.org/jira/rest/api/2/resolution/1",
            "id": "1",
            "description": "A fix for this issue is checked into the tree and tested.",
            "name": "Fixed"
        },
        "customfield_12312322": null,
        "customfield_12312323": null,
        "customfield_12312320": null,
        "customfield_12310420": "9223372036854775807",
        "customfield_12312321": null,
        "customfield_12312328": null,
        "customfield_12312329": null,
        "customfield_12312326": null,
        "customfield_12310300": null,
        "customfield_12312327": null,
        "customfield_12312324": null,
        "customfield_12312720": null,
        "customfield_12312325": null,
        "lastViewed": null,
        "priority": {
            "self": "https://issues.apache.org/jira/rest/api/2/priority/3",
            "iconUrl": "https://issues.apache.org/jira/images/icons/priorities/major.svg",
            "name": "Major",
            "id": "3"
        },
        "labels": [
            "pull-request-available"
        ],
        "customfield_12312333": null,
        "customfield_12312334": null,
        "customfield_12313422": "false",
        "customfield_12310310": "0.0",
        "customfield_12312331": null,
        "customfield_12312332": null,
        "aggregatetimeoriginalestimate": null,
        "timeestimate": 0,
        "customfield_12312330": null,
        "versions": [],
        "customfield_12311120": null,
        "customfield_12313826": null,
        "customfield_12312339": null,
        "issuelinks": [],
        "customfield_12313825": null,
        "assignee": {
            "self": "https://issues.apache.org/jira/rest/api/2/user?username=paddyhoran",
            "name": "paddyhoran",
            "key": "paddyhoran",
            "avatarUrls": {
                "48x48": "https://issues.apache.org/jira/secure/useravatar?avatarId=10452",
                "24x24": "https://issues.apache.org/jira/secure/useravatar?size=small&avatarId=10452",
                "16x16": "https://issues.apache.org/jira/secure/useravatar?size=xsmall&avatarId=10452",
                "32x32": "https://issues.apache.org/jira/secure/useravatar?size=medium&avatarId=10452"
            },
            "displayName": "Paddy Horan",
            "active": true,
            "timeZone": "America/New_York"
        },
        "customfield_12312337": null,
        "customfield_12313823": null,
        "customfield_12312338": null,
        "customfield_12311920": null,
        "customfield_12313822": null,
        "customfield_12312335": null,
        "customfield_12313821": null,
        "customfield_12312336": null,
        "customfield_12313820": null,
        "status": {
            "self": "https://issues.apache.org/jira/rest/api/2/status/5",
            "description": "A resolution has been taken, and it is awaiting verification by reporter. From here issues are either reopened, or are closed.",
            "iconUrl": "https://issues.apache.org/jira/images/icons/statuses/resolved.png",
            "name": "Resolved",
            "id": "5",
            "statusCategory": {
                "self": "https://issues.apache.org/jira/rest/api/2/statuscategory/3",
                "id": 3,
                "key": "done",
                "colorName": "green",
                "name": "Done"
            }
        },
        "components": [
            {
                "self": "https://issues.apache.org/jira/rest/api/2/component/12333773",
                "id": "12333773",
                "name": "Rust"
            }
        ],
        "customfield_12312026": null,
        "customfield_12312023": null,
        "customfield_12312024": null,
        "aggregatetimeestimate": 0,
        "customfield_12312022": null,
        "customfield_12310921": null,
        "customfield_12310920": "9223372036854775807",
        "customfield_12312823": null,
        "creator": {
            "self": "https://issues.apache.org/jira/rest/api/2/user?username=paddyhoran",
            "name": "paddyhoran",
            "key": "paddyhoran",
            "avatarUrls": {
                "48x48": "https://issues.apache.org/jira/secure/useravatar?avatarId=10452",
                "24x24": "https://issues.apache.org/jira/secure/useravatar?size=small&avatarId=10452",
                "16x16": "https://issues.apache.org/jira/secure/useravatar?size=xsmall&avatarId=10452",
                "32x32": "https://issues.apache.org/jira/secure/useravatar?size=medium&avatarId=10452"
            },
            "displayName": "Paddy Horan",
            "active": true,
            "timeZone": "America/New_York"
        },
        "subtasks": [],
        "reporter": {
            "self": "https://issues.apache.org/jira/rest/api/2/user?username=paddyhoran",
            "name": "paddyhoran",
            "key": "paddyhoran",
            "avatarUrls": {
                "48x48": "https://issues.apache.org/jira/secure/useravatar?avatarId=10452",
                "24x24": "https://issues.apache.org/jira/secure/useravatar?size=small&avatarId=10452",
                "16x16": "https://issues.apache.org/jira/secure/useravatar?size=xsmall&avatarId=10452",
                "32x32": "https://issues.apache.org/jira/secure/useravatar?size=medium&avatarId=10452"
            },
            "displayName": "Paddy Horan",
            "active": true,
            "timeZone": "America/New_York"
        },
        "aggregateprogress": {
            "progress": 6600,
            "total": 6600,
            "percent": 100
        },
        "customfield_12313520": null,
        "customfield_12310250": null,
        "progress": {
            "progress": 6600,
            "total": 6600,
            "percent": 100
        },
        "customfield_12313924": null,
        "votes": {
            "self": "https://issues.apache.org/jira/rest/api/2/issue/ARROW-4752/votes",
            "votes": 0,
            "hasVoted": false
        },
        "worklog": {
            "startAt": 0,
            "maxResults": 20,
            "total": 12,
            "worklogs": [
                {
                    "self": "https://issues.apache.org/jira/rest/api/2/issue/13219199/worklog/298123",
                    "author": {
                        "self": "https://issues.apache.org/jira/rest/api/2/user?username=githubbot",
                        "name": "githubbot",
                        "key": "githubbot",
                        "avatarUrls": {
                            "48x48": "https://issues.apache.org/jira/secure/useravatar?avatarId=10452",
                            "24x24": "https://issues.apache.org/jira/secure/useravatar?size=small&avatarId=10452",
                            "16x16": "https://issues.apache.org/jira/secure/useravatar?size=xsmall&avatarId=10452",
                            "32x32": "https://issues.apache.org/jira/secure/useravatar?size=medium&avatarId=10452"
                        },
                        "displayName": "ASF GitHub Bot",
                        "active": true,
                        "timeZone": "Etc/UTC"
                    },
                    "updateAuthor": {
                        "self": "https://issues.apache.org/jira/rest/api/2/user?username=githubbot",
                        "name": "githubbot",
                        "key": "githubbot",
                        "avatarUrls": {
                            "48x48": "https://issues.apache.org/jira/secure/useravatar?avatarId=10452",
                            "24x24": "https://issues.apache.org/jira/secure/useravatar?size=small&avatarId=10452",
                            "16x16": "https://issues.apache.org/jira/secure/useravatar?size=xsmall&avatarId=10452",
                            "32x32": "https://issues.apache.org/jira/secure/useravatar?size=medium&avatarId=10452"
                        },
                        "displayName": "ASF GitHub Bot",
                        "active": true,
                        "timeZone": "Etc/UTC"
                    },
                    "comment": "paddyhoran commented on pull request #5143: ARROW-4752: [Rust] Add explicit SIMD vectorization for the divide kernel\nURL: https://github.com/apache/arrow/pull/5143\n \n \n   \n \n----------------------------------------------------------------\nThis is an automated message from the Apache Git Service.\nTo respond to the message, please log on to GitHub and use the\nURL above to go to the specific comment.\n \nFor queries about this service, please contact Infrastructure at:\nusers@infra.apache.org\n",
                    "created": "2019-08-20T19:43:54.720+0000",
                    "updated": "2019-08-20T19:43:54.720+0000",
                    "started": "2019-08-20T19:43:54.719+0000",
                    "timeSpent": "10m",
                    "timeSpentSeconds": 600,
                    "id": "298123",
                    "issueId": "13219199"
                },
                {
                    "self": "https://issues.apache.org/jira/rest/api/2/issue/13219199/worklog/302347",
                    "author": {
                        "self": "https://issues.apache.org/jira/rest/api/2/user?username=githubbot",
                        "name": "githubbot",
                        "key": "githubbot",
                        "avatarUrls": {
                            "48x48": "https://issues.apache.org/jira/secure/useravatar?avatarId=10452",
                            "24x24": "https://issues.apache.org/jira/secure/useravatar?size=small&avatarId=10452",
                            "16x16": "https://issues.apache.org/jira/secure/useravatar?size=xsmall&avatarId=10452",
                            "32x32": "https://issues.apache.org/jira/secure/useravatar?size=medium&avatarId=10452"
                        },
                        "displayName": "ASF GitHub Bot",
                        "active": true,
                        "timeZone": "Etc/UTC"
                    },
                    "updateAuthor": {
                        "self": "https://issues.apache.org/jira/rest/api/2/user?username=githubbot",
                        "name": "githubbot",
                        "key": "githubbot",
                        "avatarUrls": {
                            "48x48": "https://issues.apache.org/jira/secure/useravatar?avatarId=10452",
                            "24x24": "https://issues.apache.org/jira/secure/useravatar?size=small&avatarId=10452",
                            "16x16": "https://issues.apache.org/jira/secure/useravatar?size=xsmall&avatarId=10452",
                            "32x32": "https://issues.apache.org/jira/secure/useravatar?size=medium&avatarId=10452"
                        },
                        "displayName": "ASF GitHub Bot",
                        "active": true,
                        "timeZone": "Etc/UTC"
                    },
                    "comment": "paddyhoran commented on issue #5143: ARROW-4752: [Rust] Add explicit SIMD vectorization for the divide kernel\nURL: https://github.com/apache/arrow/pull/5143#issuecomment-525455384\n \n \n   cc @liurenjie1024 \n \n----------------------------------------------------------------\nThis is an automated message from the Apache Git Service.\nTo respond to the message, please log on to GitHub and use the\nURL above to go to the specific comment.\n \nFor queries about this service, please contact Infrastructure at:\nusers@infra.apache.org\n",
                    "created": "2019-08-27T19:49:11.266+0000",
                    "updated": "2019-08-27T19:49:11.266+0000",
                    "started": "2019-08-27T19:49:11.265+0000",
                    "timeSpent": "10m",
                    "timeSpentSeconds": 600,
                    "id": "302347",
                    "issueId": "13219199"
                },
                {
                    "self": "https://issues.apache.org/jira/rest/api/2/issue/13219199/worklog/303356",
                    "author": {
                        "self": "https://issues.apache.org/jira/rest/api/2/user?username=githubbot",
                        "name": "githubbot",
                        "key": "githubbot",
                        "avatarUrls": {
                            "48x48": "https://issues.apache.org/jira/secure/useravatar?avatarId=10452",
                            "24x24": "https://issues.apache.org/jira/secure/useravatar?size=small&avatarId=10452",
                            "16x16": "https://issues.apache.org/jira/secure/useravatar?size=xsmall&avatarId=10452",
                            "32x32": "https://issues.apache.org/jira/secure/useravatar?size=medium&avatarId=10452"
                        },
                        "displayName": "ASF GitHub Bot",
                        "active": true,
                        "timeZone": "Etc/UTC"
                    },
                    "updateAuthor": {
                        "self": "https://issues.apache.org/jira/rest/api/2/user?username=githubbot",
                        "name": "githubbot",
                        "key": "githubbot",
                        "avatarUrls": {
                            "48x48": "https://issues.apache.org/jira/secure/useravatar?avatarId=10452",
                            "24x24": "https://issues.apache.org/jira/secure/useravatar?size=small&avatarId=10452",
                            "16x16": "https://issues.apache.org/jira/secure/useravatar?size=xsmall&avatarId=10452",
                            "32x32": "https://issues.apache.org/jira/secure/useravatar?size=medium&avatarId=10452"
                        },
                        "displayName": "ASF GitHub Bot",
                        "active": true,
                        "timeZone": "Etc/UTC"
                    },
                    "comment": "nevi-me commented on pull request #5143: ARROW-4752: [Rust] Add explicit SIMD vectorization for the divide kernel\nURL: https://github.com/apache/arrow/pull/5143#discussion_r318883969\n \n \n\n ##########\n File path: rust/arrow/src/compute/kernels/arithmetic.rs\n ##########\n @@ -121,6 +122,71 @@ where\n     Ok(PrimitiveArray::<T>::from(Arc::new(data)))\n }\n \n+/// SIMD vectorized version of `divide`, the divide kernel needs it's own implementation as there\n+/// is a need to handle situations where a divide by `0` occurs.  This is complicated by `NULL`\n+/// slots and padding.\n+#[cfg(any(target_arch = \"x86\", target_arch = \"x86_64\"))]\n+fn simd_divide<T>(\n+    left: &PrimitiveArray<T>,\n+    right: &PrimitiveArray<T>,\n+) -> Result<PrimitiveArray<T>>\n+where\n+    T: datatypes::ArrowNumericType,\n+    T::Native: One + Zero,\n+{\n+    if left.len() != right.len() {\n+        return Err(ArrowError::ComputeError(\n+            \"Cannot perform math operation on arrays of different length\".to_string(),\n+        ));\n+    }\n+\n+    // Create the combined `Bitmap`\n+    let null_bit_buffer = apply_bin_op_to_option_bitmap(\n+        left.data().null_bitmap(),\n+        right.data().null_bitmap(),\n+        |a, b| a & b,\n+    )?;\n+    let bitmap = null_bit_buffer.map(Bitmap::from);\n+\n+    let lanes = T::lanes();\n+    let buffer_size = left.len() * mem::size_of::<T::Native>();\n+    let mut result = MutableBuffer::new(buffer_size).with_bitset(buffer_size, false);\n+\n+    for i in (0..left.len()).step_by(lanes) {\n+        let right_no_invalid_zeros =\n+            unsafe { simd_load_set_invalid(right, &bitmap, i, lanes, T::Native::one()) };\n+        let is_zero = T::eq(T::init(T::Native::zero()), right_no_invalid_zeros);\n+        if T::mask_any(is_zero) {\n+            return Err(ArrowError::DivideByZero);\n+        }\n+        let right_no_invalid_zeros =\n+            unsafe { simd_load_set_invalid(right, &bitmap, i, lanes, T::Native::one()) };\n+        let simd_left = T::load(left.value_slice(i, lanes));\n+        let simd_result = T::bin_op(simd_left, right_no_invalid_zeros, |a, b| a / b);\n+\n+        let result_slice: &mut [T::Native] = unsafe {\n+            from_raw_parts_mut(\n+                (result.data_mut().as_mut_ptr() as *mut T::Native).offset(i as isize),\n+                lanes,\n+            )\n+        };\n+        T::write(simd_result, result_slice);\n+    }\n+\n+    let null_bit_buffer = bitmap.and_then(|b| Some(b.bits));\n+\n+    let data = ArrayData::new(\n \n Review comment:\n   @sunchao has previously stated preference for us using a builder, but I'm fine with this\n \n----------------------------------------------------------------\nThis is an automated message from the Apache Git Service.\nTo respond to the message, please log on to GitHub and use the\nURL above to go to the specific comment.\n \nFor queries about this service, please contact Infrastructure at:\nusers@infra.apache.org\n",
                    "created": "2019-08-29T04:53:17.395+0000",
                    "updated": "2019-08-29T04:53:17.395+0000",
                    "started": "2019-08-29T04:53:17.395+0000",
                    "timeSpent": "10m",
                    "timeSpentSeconds": 600,
                    "id": "303356",
                    "issueId": "13219199"
                },
                {
                    "self": "https://issues.apache.org/jira/rest/api/2/issue/13219199/worklog/303639",
                    "author": {
                        "self": "https://issues.apache.org/jira/rest/api/2/user?username=githubbot",
                        "name": "githubbot",
                        "key": "githubbot",
                        "avatarUrls": {
                            "48x48": "https://issues.apache.org/jira/secure/useravatar?avatarId=10452",
                            "24x24": "https://issues.apache.org/jira/secure/useravatar?size=small&avatarId=10452",
                            "16x16": "https://issues.apache.org/jira/secure/useravatar?size=xsmall&avatarId=10452",
                            "32x32": "https://issues.apache.org/jira/secure/useravatar?size=medium&avatarId=10452"
                        },
                        "displayName": "ASF GitHub Bot",
                        "active": true,
                        "timeZone": "Etc/UTC"
                    },
                    "updateAuthor": {
                        "self": "https://issues.apache.org/jira/rest/api/2/user?username=githubbot",
                        "name": "githubbot",
                        "key": "githubbot",
                        "avatarUrls": {
                            "48x48": "https://issues.apache.org/jira/secure/useravatar?avatarId=10452",
                            "24x24": "https://issues.apache.org/jira/secure/useravatar?size=small&avatarId=10452",
                            "16x16": "https://issues.apache.org/jira/secure/useravatar?size=xsmall&avatarId=10452",
                            "32x32": "https://issues.apache.org/jira/secure/useravatar?size=medium&avatarId=10452"
                        },
                        "displayName": "ASF GitHub Bot",
                        "active": true,
                        "timeZone": "Etc/UTC"
                    },
                    "comment": "paddyhoran commented on pull request #5143: ARROW-4752: [Rust] Add explicit SIMD vectorization for the divide kernel\nURL: https://github.com/apache/arrow/pull/5143#discussion_r319035237\n \n \n\n ##########\n File path: rust/arrow/src/compute/kernels/arithmetic.rs\n ##########\n @@ -121,6 +122,71 @@ where\n     Ok(PrimitiveArray::<T>::from(Arc::new(data)))\n }\n \n+/// SIMD vectorized version of `divide`, the divide kernel needs it's own implementation as there\n+/// is a need to handle situations where a divide by `0` occurs.  This is complicated by `NULL`\n+/// slots and padding.\n+#[cfg(any(target_arch = \"x86\", target_arch = \"x86_64\"))]\n+fn simd_divide<T>(\n+    left: &PrimitiveArray<T>,\n+    right: &PrimitiveArray<T>,\n+) -> Result<PrimitiveArray<T>>\n+where\n+    T: datatypes::ArrowNumericType,\n+    T::Native: One + Zero,\n+{\n+    if left.len() != right.len() {\n+        return Err(ArrowError::ComputeError(\n+            \"Cannot perform math operation on arrays of different length\".to_string(),\n+        ));\n+    }\n+\n+    // Create the combined `Bitmap`\n+    let null_bit_buffer = apply_bin_op_to_option_bitmap(\n+        left.data().null_bitmap(),\n+        right.data().null_bitmap(),\n+        |a, b| a & b,\n+    )?;\n+    let bitmap = null_bit_buffer.map(Bitmap::from);\n+\n+    let lanes = T::lanes();\n+    let buffer_size = left.len() * mem::size_of::<T::Native>();\n+    let mut result = MutableBuffer::new(buffer_size).with_bitset(buffer_size, false);\n+\n+    for i in (0..left.len()).step_by(lanes) {\n+        let right_no_invalid_zeros =\n+            unsafe { simd_load_set_invalid(right, &bitmap, i, lanes, T::Native::one()) };\n+        let is_zero = T::eq(T::init(T::Native::zero()), right_no_invalid_zeros);\n+        if T::mask_any(is_zero) {\n+            return Err(ArrowError::DivideByZero);\n+        }\n+        let right_no_invalid_zeros =\n+            unsafe { simd_load_set_invalid(right, &bitmap, i, lanes, T::Native::one()) };\n+        let simd_left = T::load(left.value_slice(i, lanes));\n+        let simd_result = T::bin_op(simd_left, right_no_invalid_zeros, |a, b| a / b);\n+\n+        let result_slice: &mut [T::Native] = unsafe {\n+            from_raw_parts_mut(\n+                (result.data_mut().as_mut_ptr() as *mut T::Native).offset(i as isize),\n+                lanes,\n+            )\n+        };\n+        T::write(simd_result, result_slice);\n+    }\n+\n+    let null_bit_buffer = bitmap.and_then(|b| Some(b.bits));\n+\n+    let data = ArrayData::new(\n \n Review comment:\n   I don't have an issue with that, I'll switch it to use the builder\n \n----------------------------------------------------------------\nThis is an automated message from the Apache Git Service.\nTo respond to the message, please log on to GitHub and use the\nURL above to go to the specific comment.\n \nFor queries about this service, please contact Infrastructure at:\nusers@infra.apache.org\n",
                    "created": "2019-08-29T12:14:59.995+0000",
                    "updated": "2019-08-29T12:14:59.995+0000",
                    "started": "2019-08-29T12:14:59.994+0000",
                    "timeSpent": "10m",
                    "timeSpentSeconds": 600,
                    "id": "303639",
                    "issueId": "13219199"
                },
                {
                    "self": "https://issues.apache.org/jira/rest/api/2/issue/13219199/worklog/304828",
                    "author": {
                        "self": "https://issues.apache.org/jira/rest/api/2/user?username=githubbot",
                        "name": "githubbot",
                        "key": "githubbot",
                        "avatarUrls": {
                            "48x48": "https://issues.apache.org/jira/secure/useravatar?avatarId=10452",
                            "24x24": "https://issues.apache.org/jira/secure/useravatar?size=small&avatarId=10452",
                            "16x16": "https://issues.apache.org/jira/secure/useravatar?size=xsmall&avatarId=10452",
                            "32x32": "https://issues.apache.org/jira/secure/useravatar?size=medium&avatarId=10452"
                        },
                        "displayName": "ASF GitHub Bot",
                        "active": true,
                        "timeZone": "Etc/UTC"
                    },
                    "updateAuthor": {
                        "self": "https://issues.apache.org/jira/rest/api/2/user?username=githubbot",
                        "name": "githubbot",
                        "key": "githubbot",
                        "avatarUrls": {
                            "48x48": "https://issues.apache.org/jira/secure/useravatar?avatarId=10452",
                            "24x24": "https://issues.apache.org/jira/secure/useravatar?size=small&avatarId=10452",
                            "16x16": "https://issues.apache.org/jira/secure/useravatar?size=xsmall&avatarId=10452",
                            "32x32": "https://issues.apache.org/jira/secure/useravatar?size=medium&avatarId=10452"
                        },
                        "displayName": "ASF GitHub Bot",
                        "active": true,
                        "timeZone": "Etc/UTC"
                    },
                    "comment": "liurenjie1024 commented on pull request #5143: ARROW-4752: [Rust] Add explicit SIMD vectorization for the divide kernel\nURL: https://github.com/apache/arrow/pull/5143#discussion_r319717518\n \n \n\n ##########\n File path: rust/arrow/src/compute/kernels/arithmetic.rs\n ##########\n @@ -197,8 +263,13 @@ where\n         + Sub<Output = T::Native>\n         + Mul<Output = T::Native>\n         + Div<Output = T::Native>\n-        + Zero,\n+        + Zero\n+        + One,\n {\n+    #[cfg(any(target_arch = \"x86\", target_arch = \"x86_64\"))]\n+    return simd_divide(&left, &right);\n \n Review comment:\n   Is it more readable to use the \r\n   `if cfg!`\r\n   pattern?\n \n----------------------------------------------------------------\nThis is an automated message from the Apache Git Service.\nTo respond to the message, please log on to GitHub and use the\nURL above to go to the specific comment.\n \nFor queries about this service, please contact Infrastructure at:\nusers@infra.apache.org\n",
                    "created": "2019-08-31T09:21:21.395+0000",
                    "updated": "2019-08-31T09:21:21.395+0000",
                    "started": "2019-08-31T09:21:21.395+0000",
                    "timeSpent": "10m",
                    "timeSpentSeconds": 600,
                    "id": "304828",
                    "issueId": "13219199"
                },
                {
                    "self": "https://issues.apache.org/jira/rest/api/2/issue/13219199/worklog/304829",
                    "author": {
                        "self": "https://issues.apache.org/jira/rest/api/2/user?username=githubbot",
                        "name": "githubbot",
                        "key": "githubbot",
                        "avatarUrls": {
                            "48x48": "https://issues.apache.org/jira/secure/useravatar?avatarId=10452",
                            "24x24": "https://issues.apache.org/jira/secure/useravatar?size=small&avatarId=10452",
                            "16x16": "https://issues.apache.org/jira/secure/useravatar?size=xsmall&avatarId=10452",
                            "32x32": "https://issues.apache.org/jira/secure/useravatar?size=medium&avatarId=10452"
                        },
                        "displayName": "ASF GitHub Bot",
                        "active": true,
                        "timeZone": "Etc/UTC"
                    },
                    "updateAuthor": {
                        "self": "https://issues.apache.org/jira/rest/api/2/user?username=githubbot",
                        "name": "githubbot",
                        "key": "githubbot",
                        "avatarUrls": {
                            "48x48": "https://issues.apache.org/jira/secure/useravatar?avatarId=10452",
                            "24x24": "https://issues.apache.org/jira/secure/useravatar?size=small&avatarId=10452",
                            "16x16": "https://issues.apache.org/jira/secure/useravatar?size=xsmall&avatarId=10452",
                            "32x32": "https://issues.apache.org/jira/secure/useravatar?size=medium&avatarId=10452"
                        },
                        "displayName": "ASF GitHub Bot",
                        "active": true,
                        "timeZone": "Etc/UTC"
                    },
                    "comment": "liurenjie1024 commented on pull request #5143: ARROW-4752: [Rust] Add explicit SIMD vectorization for the divide kernel\nURL: https://github.com/apache/arrow/pull/5143#discussion_r319717534\n \n \n\n ##########\n File path: rust/arrow/src/compute/kernels/arithmetic.rs\n ##########\n @@ -274,6 +345,19 @@ mod tests {\n         assert_eq!(9, c.value(4));\n     }\n \n+    #[test]\n+    fn test_primitive_array_divide_with_nulls() {\n \n Review comment:\n   I would suggest to use template to covert all numeric types in test.\n \n----------------------------------------------------------------\nThis is an automated message from the Apache Git Service.\nTo respond to the message, please log on to GitHub and use the\nURL above to go to the specific comment.\n \nFor queries about this service, please contact Infrastructure at:\nusers@infra.apache.org\n",
                    "created": "2019-08-31T09:21:21.398+0000",
                    "updated": "2019-08-31T09:21:21.398+0000",
                    "started": "2019-08-31T09:21:21.398+0000",
                    "timeSpent": "10m",
                    "timeSpentSeconds": 600,
                    "id": "304829",
                    "issueId": "13219199"
                },
                {
                    "self": "https://issues.apache.org/jira/rest/api/2/issue/13219199/worklog/304931",
                    "author": {
                        "self": "https://issues.apache.org/jira/rest/api/2/user?username=githubbot",
                        "name": "githubbot",
                        "key": "githubbot",
                        "avatarUrls": {
                            "48x48": "https://issues.apache.org/jira/secure/useravatar?avatarId=10452",
                            "24x24": "https://issues.apache.org/jira/secure/useravatar?size=small&avatarId=10452",
                            "16x16": "https://issues.apache.org/jira/secure/useravatar?size=xsmall&avatarId=10452",
                            "32x32": "https://issues.apache.org/jira/secure/useravatar?size=medium&avatarId=10452"
                        },
                        "displayName": "ASF GitHub Bot",
                        "active": true,
                        "timeZone": "Etc/UTC"
                    },
                    "updateAuthor": {
                        "self": "https://issues.apache.org/jira/rest/api/2/user?username=githubbot",
                        "name": "githubbot",
                        "key": "githubbot",
                        "avatarUrls": {
                            "48x48": "https://issues.apache.org/jira/secure/useravatar?avatarId=10452",
                            "24x24": "https://issues.apache.org/jira/secure/useravatar?size=small&avatarId=10452",
                            "16x16": "https://issues.apache.org/jira/secure/useravatar?size=xsmall&avatarId=10452",
                            "32x32": "https://issues.apache.org/jira/secure/useravatar?size=medium&avatarId=10452"
                        },
                        "displayName": "ASF GitHub Bot",
                        "active": true,
                        "timeZone": "Etc/UTC"
                    },
                    "comment": "paddyhoran commented on pull request #5143: ARROW-4752: [Rust] Add explicit SIMD vectorization for the divide kernel\nURL: https://github.com/apache/arrow/pull/5143#discussion_r319740280\n \n \n\n ##########\n File path: rust/arrow/src/compute/kernels/arithmetic.rs\n ##########\n @@ -274,6 +345,19 @@ mod tests {\n         assert_eq!(9, c.value(4));\n     }\n \n+    #[test]\n+    fn test_primitive_array_divide_with_nulls() {\n \n Review comment:\n   @liurenjie1024 I'm not sure what you mean, could you explain?\n \n----------------------------------------------------------------\nThis is an automated message from the Apache Git Service.\nTo respond to the message, please log on to GitHub and use the\nURL above to go to the specific comment.\n \nFor queries about this service, please contact Infrastructure at:\nusers@infra.apache.org\n",
                    "created": "2019-09-01T00:59:57.314+0000",
                    "updated": "2019-09-01T00:59:57.314+0000",
                    "started": "2019-09-01T00:59:57.313+0000",
                    "timeSpent": "10m",
                    "timeSpentSeconds": 600,
                    "id": "304931",
                    "issueId": "13219199"
                },
                {
                    "self": "https://issues.apache.org/jira/rest/api/2/issue/13219199/worklog/304954",
                    "author": {
                        "self": "https://issues.apache.org/jira/rest/api/2/user?username=githubbot",
                        "name": "githubbot",
                        "key": "githubbot",
                        "avatarUrls": {
                            "48x48": "https://issues.apache.org/jira/secure/useravatar?avatarId=10452",
                            "24x24": "https://issues.apache.org/jira/secure/useravatar?size=small&avatarId=10452",
                            "16x16": "https://issues.apache.org/jira/secure/useravatar?size=xsmall&avatarId=10452",
                            "32x32": "https://issues.apache.org/jira/secure/useravatar?size=medium&avatarId=10452"
                        },
                        "displayName": "ASF GitHub Bot",
                        "active": true,
                        "timeZone": "Etc/UTC"
                    },
                    "updateAuthor": {
                        "self": "https://issues.apache.org/jira/rest/api/2/user?username=githubbot",
                        "name": "githubbot",
                        "key": "githubbot",
                        "avatarUrls": {
                            "48x48": "https://issues.apache.org/jira/secure/useravatar?avatarId=10452",
                            "24x24": "https://issues.apache.org/jira/secure/useravatar?size=small&avatarId=10452",
                            "16x16": "https://issues.apache.org/jira/secure/useravatar?size=xsmall&avatarId=10452",
                            "32x32": "https://issues.apache.org/jira/secure/useravatar?size=medium&avatarId=10452"
                        },
                        "displayName": "ASF GitHub Bot",
                        "active": true,
                        "timeZone": "Etc/UTC"
                    },
                    "comment": "liurenjie1024 commented on pull request #5143: ARROW-4752: [Rust] Add explicit SIMD vectorization for the divide kernel\nURL: https://github.com/apache/arrow/pull/5143#discussion_r319745648\n \n \n\n ##########\n File path: rust/arrow/src/compute/kernels/arithmetic.rs\n ##########\n @@ -274,6 +345,19 @@ mod tests {\n         assert_eq!(9, c.value(4));\n     }\n \n+    #[test]\n+    fn test_primitive_array_divide_with_nulls() {\n \n Review comment:\n   I mean maybe we should cover all numerics types, not just int32?\n \n----------------------------------------------------------------\nThis is an automated message from the Apache Git Service.\nTo respond to the message, please log on to GitHub and use the\nURL above to go to the specific comment.\n \nFor queries about this service, please contact Infrastructure at:\nusers@infra.apache.org\n",
                    "created": "2019-09-01T06:49:12.717+0000",
                    "updated": "2019-09-01T06:49:12.717+0000",
                    "started": "2019-09-01T06:49:12.717+0000",
                    "timeSpent": "10m",
                    "timeSpentSeconds": 600,
                    "id": "304954",
                    "issueId": "13219199"
                },
                {
                    "self": "https://issues.apache.org/jira/rest/api/2/issue/13219199/worklog/304978",
                    "author": {
                        "self": "https://issues.apache.org/jira/rest/api/2/user?username=githubbot",
                        "name": "githubbot",
                        "key": "githubbot",
                        "avatarUrls": {
                            "48x48": "https://issues.apache.org/jira/secure/useravatar?avatarId=10452",
                            "24x24": "https://issues.apache.org/jira/secure/useravatar?size=small&avatarId=10452",
                            "16x16": "https://issues.apache.org/jira/secure/useravatar?size=xsmall&avatarId=10452",
                            "32x32": "https://issues.apache.org/jira/secure/useravatar?size=medium&avatarId=10452"
                        },
                        "displayName": "ASF GitHub Bot",
                        "active": true,
                        "timeZone": "Etc/UTC"
                    },
                    "updateAuthor": {
                        "self": "https://issues.apache.org/jira/rest/api/2/user?username=githubbot",
                        "name": "githubbot",
                        "key": "githubbot",
                        "avatarUrls": {
                            "48x48": "https://issues.apache.org/jira/secure/useravatar?avatarId=10452",
                            "24x24": "https://issues.apache.org/jira/secure/useravatar?size=small&avatarId=10452",
                            "16x16": "https://issues.apache.org/jira/secure/useravatar?size=xsmall&avatarId=10452",
                            "32x32": "https://issues.apache.org/jira/secure/useravatar?size=medium&avatarId=10452"
                        },
                        "displayName": "ASF GitHub Bot",
                        "active": true,
                        "timeZone": "Etc/UTC"
                    },
                    "comment": "andygrove commented on pull request #5143: ARROW-4752: [Rust] Add explicit SIMD vectorization for the divide kernel\nURL: https://github.com/apache/arrow/pull/5143\n \n \n   \n \n----------------------------------------------------------------\nThis is an automated message from the Apache Git Service.\nTo respond to the message, please log on to GitHub and use the\nURL above to go to the specific comment.\n \nFor queries about this service, please contact Infrastructure at:\nusers@infra.apache.org\n",
                    "created": "2019-09-01T15:25:15.485+0000",
                    "updated": "2019-09-01T15:25:15.485+0000",
                    "started": "2019-09-01T15:25:15.484+0000",
                    "timeSpent": "10m",
                    "timeSpentSeconds": 600,
                    "id": "304978",
                    "issueId": "13219199"
                },
                {
                    "self": "https://issues.apache.org/jira/rest/api/2/issue/13219199/worklog/304990",
                    "author": {
                        "self": "https://issues.apache.org/jira/rest/api/2/user?username=githubbot",
                        "name": "githubbot",
                        "key": "githubbot",
                        "avatarUrls": {
                            "48x48": "https://issues.apache.org/jira/secure/useravatar?avatarId=10452",
                            "24x24": "https://issues.apache.org/jira/secure/useravatar?size=small&avatarId=10452",
                            "16x16": "https://issues.apache.org/jira/secure/useravatar?size=xsmall&avatarId=10452",
                            "32x32": "https://issues.apache.org/jira/secure/useravatar?size=medium&avatarId=10452"
                        },
                        "displayName": "ASF GitHub Bot",
                        "active": true,
                        "timeZone": "Etc/UTC"
                    },
                    "updateAuthor": {
                        "self": "https://issues.apache.org/jira/rest/api/2/user?username=githubbot",
                        "name": "githubbot",
                        "key": "githubbot",
                        "avatarUrls": {
                            "48x48": "https://issues.apache.org/jira/secure/useravatar?avatarId=10452",
                            "24x24": "https://issues.apache.org/jira/secure/useravatar?size=small&avatarId=10452",
                            "16x16": "https://issues.apache.org/jira/secure/useravatar?size=xsmall&avatarId=10452",
                            "32x32": "https://issues.apache.org/jira/secure/useravatar?size=medium&avatarId=10452"
                        },
                        "displayName": "ASF GitHub Bot",
                        "active": true,
                        "timeZone": "Etc/UTC"
                    },
                    "comment": "paddyhoran commented on pull request #5143: ARROW-4752: [Rust] Add explicit SIMD vectorization for the divide kernel\nURL: https://github.com/apache/arrow/pull/5143#discussion_r319768102\n \n \n\n ##########\n File path: rust/arrow/src/compute/kernels/arithmetic.rs\n ##########\n @@ -121,6 +122,71 @@ where\n     Ok(PrimitiveArray::<T>::from(Arc::new(data)))\n }\n \n+/// SIMD vectorized version of `divide`, the divide kernel needs it's own implementation as there\n+/// is a need to handle situations where a divide by `0` occurs.  This is complicated by `NULL`\n+/// slots and padding.\n+#[cfg(any(target_arch = \"x86\", target_arch = \"x86_64\"))]\n+fn simd_divide<T>(\n+    left: &PrimitiveArray<T>,\n+    right: &PrimitiveArray<T>,\n+) -> Result<PrimitiveArray<T>>\n+where\n+    T: datatypes::ArrowNumericType,\n+    T::Native: One + Zero,\n+{\n+    if left.len() != right.len() {\n+        return Err(ArrowError::ComputeError(\n+            \"Cannot perform math operation on arrays of different length\".to_string(),\n+        ));\n+    }\n+\n+    // Create the combined `Bitmap`\n+    let null_bit_buffer = apply_bin_op_to_option_bitmap(\n+        left.data().null_bitmap(),\n+        right.data().null_bitmap(),\n+        |a, b| a & b,\n+    )?;\n+    let bitmap = null_bit_buffer.map(Bitmap::from);\n+\n+    let lanes = T::lanes();\n+    let buffer_size = left.len() * mem::size_of::<T::Native>();\n+    let mut result = MutableBuffer::new(buffer_size).with_bitset(buffer_size, false);\n+\n+    for i in (0..left.len()).step_by(lanes) {\n+        let right_no_invalid_zeros =\n+            unsafe { simd_load_set_invalid(right, &bitmap, i, lanes, T::Native::one()) };\n+        let is_zero = T::eq(T::init(T::Native::zero()), right_no_invalid_zeros);\n+        if T::mask_any(is_zero) {\n+            return Err(ArrowError::DivideByZero);\n+        }\n+        let right_no_invalid_zeros =\n+            unsafe { simd_load_set_invalid(right, &bitmap, i, lanes, T::Native::one()) };\n+        let simd_left = T::load(left.value_slice(i, lanes));\n+        let simd_result = T::bin_op(simd_left, right_no_invalid_zeros, |a, b| a / b);\n+\n+        let result_slice: &mut [T::Native] = unsafe {\n+            from_raw_parts_mut(\n+                (result.data_mut().as_mut_ptr() as *mut T::Native).offset(i as isize),\n+                lanes,\n+            )\n+        };\n+        T::write(simd_result, result_slice);\n+    }\n+\n+    let null_bit_buffer = bitmap.and_then(|b| Some(b.bits));\n+\n+    let data = ArrayData::new(\n \n Review comment:\n   So I remember why I didn't use the builder now.  `null_bit_buffer` is an `Option<Bitmap>`.  There is no method on the builder that accepts an `Option<Bitmap>` only one that accepts `Bitmap` which leads to a match on `null_bit_buffer` which is not very clean.  `new` accepts the `Option<Bitmap>` directly.\n \n----------------------------------------------------------------\nThis is an automated message from the Apache Git Service.\nTo respond to the message, please log on to GitHub and use the\nURL above to go to the specific comment.\n \nFor queries about this service, please contact Infrastructure at:\nusers@infra.apache.org\n",
                    "created": "2019-09-01T17:15:10.770+0000",
                    "updated": "2019-09-01T17:15:10.770+0000",
                    "started": "2019-09-01T17:15:10.769+0000",
                    "timeSpent": "10m",
                    "timeSpentSeconds": 600,
                    "id": "304990",
                    "issueId": "13219199"
                },
                {
                    "self": "https://issues.apache.org/jira/rest/api/2/issue/13219199/worklog/304992",
                    "author": {
                        "self": "https://issues.apache.org/jira/rest/api/2/user?username=githubbot",
                        "name": "githubbot",
                        "key": "githubbot",
                        "avatarUrls": {
                            "48x48": "https://issues.apache.org/jira/secure/useravatar?avatarId=10452",
                            "24x24": "https://issues.apache.org/jira/secure/useravatar?size=small&avatarId=10452",
                            "16x16": "https://issues.apache.org/jira/secure/useravatar?size=xsmall&avatarId=10452",
                            "32x32": "https://issues.apache.org/jira/secure/useravatar?size=medium&avatarId=10452"
                        },
                        "displayName": "ASF GitHub Bot",
                        "active": true,
                        "timeZone": "Etc/UTC"
                    },
                    "updateAuthor": {
                        "self": "https://issues.apache.org/jira/rest/api/2/user?username=githubbot",
                        "name": "githubbot",
                        "key": "githubbot",
                        "avatarUrls": {
                            "48x48": "https://issues.apache.org/jira/secure/useravatar?avatarId=10452",
                            "24x24": "https://issues.apache.org/jira/secure/useravatar?size=small&avatarId=10452",
                            "16x16": "https://issues.apache.org/jira/secure/useravatar?size=xsmall&avatarId=10452",
                            "32x32": "https://issues.apache.org/jira/secure/useravatar?size=medium&avatarId=10452"
                        },
                        "displayName": "ASF GitHub Bot",
                        "active": true,
                        "timeZone": "Etc/UTC"
                    },
                    "comment": "paddyhoran commented on pull request #5143: ARROW-4752: [Rust] Add explicit SIMD vectorization for the divide kernel\nURL: https://github.com/apache/arrow/pull/5143#discussion_r319768308\n \n \n\n ##########\n File path: rust/arrow/src/compute/kernels/arithmetic.rs\n ##########\n @@ -197,8 +263,13 @@ where\n         + Sub<Output = T::Native>\n         + Mul<Output = T::Native>\n         + Div<Output = T::Native>\n-        + Zero,\n+        + Zero\n+        + One,\n {\n+    #[cfg(any(target_arch = \"x86\", target_arch = \"x86_64\"))]\n+    return simd_divide(&left, &right);\n \n Review comment:\n   Follow up JIRA is [here](https://issues.apache.org/jira/browse/ARROW-6408?filter=-2).\n \n----------------------------------------------------------------\nThis is an automated message from the Apache Git Service.\nTo respond to the message, please log on to GitHub and use the\nURL above to go to the specific comment.\n \nFor queries about this service, please contact Infrastructure at:\nusers@infra.apache.org\n",
                    "created": "2019-09-01T17:21:44.490+0000",
                    "updated": "2019-09-01T17:21:44.490+0000",
                    "started": "2019-09-01T17:21:44.489+0000",
                    "timeSpent": "10m",
                    "timeSpentSeconds": 600,
                    "id": "304992",
                    "issueId": "13219199"
                },
                {
                    "self": "https://issues.apache.org/jira/rest/api/2/issue/13219199/worklog/304993",
                    "author": {
                        "self": "https://issues.apache.org/jira/rest/api/2/user?username=githubbot",
                        "name": "githubbot",
                        "key": "githubbot",
                        "avatarUrls": {
                            "48x48": "https://issues.apache.org/jira/secure/useravatar?avatarId=10452",
                            "24x24": "https://issues.apache.org/jira/secure/useravatar?size=small&avatarId=10452",
                            "16x16": "https://issues.apache.org/jira/secure/useravatar?size=xsmall&avatarId=10452",
                            "32x32": "https://issues.apache.org/jira/secure/useravatar?size=medium&avatarId=10452"
                        },
                        "displayName": "ASF GitHub Bot",
                        "active": true,
                        "timeZone": "Etc/UTC"
                    },
                    "updateAuthor": {
                        "self": "https://issues.apache.org/jira/rest/api/2/user?username=githubbot",
                        "name": "githubbot",
                        "key": "githubbot",
                        "avatarUrls": {
                            "48x48": "https://issues.apache.org/jira/secure/useravatar?avatarId=10452",
                            "24x24": "https://issues.apache.org/jira/secure/useravatar?size=small&avatarId=10452",
                            "16x16": "https://issues.apache.org/jira/secure/useravatar?size=xsmall&avatarId=10452",
                            "32x32": "https://issues.apache.org/jira/secure/useravatar?size=medium&avatarId=10452"
                        },
                        "displayName": "ASF GitHub Bot",
                        "active": true,
                        "timeZone": "Etc/UTC"
                    },
                    "comment": "paddyhoran commented on pull request #5143: ARROW-4752: [Rust] Add explicit SIMD vectorization for the divide kernel\nURL: https://github.com/apache/arrow/pull/5143#discussion_r319768414\n \n \n\n ##########\n File path: rust/arrow/src/compute/kernels/arithmetic.rs\n ##########\n @@ -274,6 +345,19 @@ mod tests {\n         assert_eq!(9, c.value(4));\n     }\n \n+    #[test]\n+    fn test_primitive_array_divide_with_nulls() {\n \n Review comment:\n   Ok, yep good point.  Follow up JIRA is [here](https://issues.apache.org/jira/browse/ARROW-6409?filter=-2)\n \n----------------------------------------------------------------\nThis is an automated message from the Apache Git Service.\nTo respond to the message, please log on to GitHub and use the\nURL above to go to the specific comment.\n \nFor queries about this service, please contact Infrastructure at:\nusers@infra.apache.org\n",
                    "created": "2019-09-01T17:25:21.253+0000",
                    "updated": "2019-09-01T17:25:21.253+0000",
                    "started": "2019-09-01T17:25:21.253+0000",
                    "timeSpent": "10m",
                    "timeSpentSeconds": 600,
                    "id": "304993",
                    "issueId": "13219199"
                }
            ]
        },
        "customfield_12313920": null,
        "issuetype": {
            "self": "https://issues.apache.org/jira/rest/api/2/issuetype/4",
            "id": "4",
            "description": "An improvement or enhancement to an existing feature or task.",
            "iconUrl": "https://issues.apache.org/jira/secure/viewavatar?size=xsmall&avatarId=21140&avatarType=issuetype",
            "name": "Improvement",
            "subtask": false,
            "avatarId": 21140
        },
        "timespent": 6600,
        "customfield_12314020": "{summaryBean=com.atlassian.jira.plugin.devstatus.rest.SummaryBean@78592ef8[summary={pullrequest=com.atlassian.jira.plugin.devstatus.rest.SummaryItemBean@6f8e46a[overall=PullRequestOverallBean{stateCount=0, state='OPEN', details=PullRequestOverallDetails{openCount=0, mergedCount=0, declinedCount=0}},byInstanceType={}], build=com.atlassian.jira.plugin.devstatus.rest.SummaryItemBean@1ff3c7ef[overall=com.atlassian.jira.plugin.devstatus.summary.beans.BuildOverallBean@5e69abcf[failedBuildCount=0,successfulBuildCount=0,unknownBuildCount=0,count=0,lastUpdated=<null>,lastUpdatedTimestamp=<null>],byInstanceType={}], review=com.atlassian.jira.plugin.devstatus.rest.SummaryItemBean@3d83230a[overall=com.atlassian.jira.plugin.devstatus.summary.beans.ReviewsOverallBean@7330ebbc[stateCount=0,state=<null>,dueDate=<null>,overDue=false,count=0,lastUpdated=<null>,lastUpdatedTimestamp=<null>],byInstanceType={}], deployment-environment=com.atlassian.jira.plugin.devstatus.rest.SummaryItemBean@727d868a[overall=com.atlassian.jira.plugin.devstatus.summary.beans.DeploymentOverallBean@61596cd9[topEnvironments=[],showProjects=false,successfulCount=0,count=0,lastUpdated=<null>,lastUpdatedTimestamp=<null>],byInstanceType={}], repository=com.atlassian.jira.plugin.devstatus.rest.SummaryItemBean@4566888b[overall=com.atlassian.jira.plugin.devstatus.summary.beans.CommitOverallBean@317ff690[count=0,lastUpdated=<null>,lastUpdatedTimestamp=<null>],byInstanceType={}], branch=com.atlassian.jira.plugin.devstatus.rest.SummaryItemBean@2fa87fe3[overall=com.atlassian.jira.plugin.devstatus.summary.beans.BranchOverallBean@53de16b[count=0,lastUpdated=<null>,lastUpdatedTimestamp=<null>],byInstanceType={}]},errors=[],configErrors=[]], devSummaryJson={\"cachedValue\":{\"errors\":[],\"configErrors\":[],\"summary\":{\"pullrequest\":{\"overall\":{\"count\":0,\"lastUpdated\":null,\"stateCount\":0,\"state\":\"OPEN\",\"details\":{\"openCount\":0,\"mergedCount\":0,\"declinedCount\":0,\"total\":0},\"open\":true},\"byInstanceType\":{}},\"build\":{\"overall\":{\"count\":0,\"lastUpdated\":null,\"failedBuildCount\":0,\"successfulBuildCount\":0,\"unknownBuildCount\":0},\"byInstanceType\":{}},\"review\":{\"overall\":{\"count\":0,\"lastUpdated\":null,\"stateCount\":0,\"state\":null,\"dueDate\":null,\"overDue\":false,\"completed\":false},\"byInstanceType\":{}},\"deployment-environment\":{\"overall\":{\"count\":0,\"lastUpdated\":null,\"topEnvironments\":[],\"showProjects\":false,\"successfulCount\":0},\"byInstanceType\":{}},\"repository\":{\"overall\":{\"count\":0,\"lastUpdated\":null},\"byInstanceType\":{}},\"branch\":{\"overall\":{\"count\":0,\"lastUpdated\":null},\"byInstanceType\":{}}}},\"isStale\":false}}",
        "customfield_12314141": null,
        "customfield_12314140": null,
        "project": {
            "self": "https://issues.apache.org/jira/rest/api/2/project/12319525",
            "id": "12319525",
            "key": "ARROW",
            "name": "Apache Arrow",
            "projectTypeKey": "software",
            "avatarUrls": {
                "48x48": "https://issues.apache.org/jira/secure/projectavatar?pid=12319525&avatarId=10011",
                "24x24": "https://issues.apache.org/jira/secure/projectavatar?size=small&pid=12319525&avatarId=10011",
                "16x16": "https://issues.apache.org/jira/secure/projectavatar?size=xsmall&pid=12319525&avatarId=10011",
                "32x32": "https://issues.apache.org/jira/secure/projectavatar?size=medium&pid=12319525&avatarId=10011"
            },
            "projectCategory": {
                "self": "https://issues.apache.org/jira/rest/api/2/projectCategory/13960",
                "id": "13960",
                "description": "Apache Arrow",
                "name": "Arrow"
            }
        },
        "aggregatetimespent": 6600,
        "customfield_12312520": null,
        "customfield_12312521": "Sun Sep 01 15:25:13 UTC 2019",
        "customfield_12314422": null,
        "customfield_12314421": null,
        "customfield_12314146": null,
        "customfield_12314420": null,
        "customfield_12314145": null,
        "customfield_12314144": null,
        "customfield_12314143": null,
        "resolutiondate": "2019-09-01T15:25:13.000+0000",
        "workratio": -1,
        "customfield_12312923": null,
        "customfield_12312920": null,
        "customfield_12312921": null,
        "watches": {
            "self": "https://issues.apache.org/jira/rest/api/2/issue/ARROW-4752/watchers",
            "watchCount": 1,
            "isWatching": false
        },
        "created": "2019-03-04T03:42:52.000+0000",
        "updated": "2019-09-01T17:25:21.000+0000",
        "timeoriginalestimate": null,
        "description": null,
        "customfield_10010": null,
        "timetracking": {
            "remainingEstimate": "0h",
            "timeSpent": "1h 50m",
            "remainingEstimateSeconds": 0,
            "timeSpentSeconds": 6600
        },
        "customfield_12314523": null,
        "customfield_12314127": null,
        "customfield_12314522": null,
        "customfield_12314126": null,
        "customfield_12314521": null,
        "customfield_12314125": null,
        "customfield_12314520": null,
        "customfield_12314124": null,
        "attachment": [],
        "customfield_12312340": null,
        "customfield_12314123": null,
        "customfield_12312341": null,
        "customfield_12312220": null,
        "customfield_12314122": null,
        "customfield_12314121": null,
        "customfield_12314120": null,
        "customfield_12314129": null,
        "customfield_12314524": null,
        "customfield_12314128": null,
        "summary": "[Rust] Add explicit SIMD vectorization for the divide kernel",
        "customfield_12314130": null,
        "customfield_12310291": null,
        "customfield_12310290": null,
        "customfield_12314138": null,
        "customfield_12314137": null,
        "environment": null,
        "customfield_12314136": null,
        "customfield_12314135": null,
        "customfield_12311020": null,
        "customfield_12314134": null,
        "duedate": null,
        "customfield_12314132": null,
        "customfield_12314131": null,
        "comment": {
            "comments": [
                {
                    "self": "https://issues.apache.org/jira/rest/api/2/issue/13219199/comment/16920415",
                    "id": "16920415",
                    "author": {
                        "self": "https://issues.apache.org/jira/rest/api/2/user?username=andygrove",
                        "name": "andygrove",
                        "key": "andygrove",
                        "avatarUrls": {
                            "48x48": "https://issues.apache.org/jira/secure/useravatar?ownerId=andygrove&avatarId=28239",
                            "24x24": "https://issues.apache.org/jira/secure/useravatar?size=small&ownerId=andygrove&avatarId=28239",
                            "16x16": "https://issues.apache.org/jira/secure/useravatar?size=xsmall&ownerId=andygrove&avatarId=28239",
                            "32x32": "https://issues.apache.org/jira/secure/useravatar?size=medium&ownerId=andygrove&avatarId=28239"
                        },
                        "displayName": "Andy Grove",
                        "active": true,
                        "timeZone": "America/Denver"
                    },
                    "body": "Issue resolved by pull request 5143\n[https://github.com/apache/arrow/pull/5143]",
                    "updateAuthor": {
                        "self": "https://issues.apache.org/jira/rest/api/2/user?username=andygrove",
                        "name": "andygrove",
                        "key": "andygrove",
                        "avatarUrls": {
                            "48x48": "https://issues.apache.org/jira/secure/useravatar?ownerId=andygrove&avatarId=28239",
                            "24x24": "https://issues.apache.org/jira/secure/useravatar?size=small&ownerId=andygrove&avatarId=28239",
                            "16x16": "https://issues.apache.org/jira/secure/useravatar?size=xsmall&ownerId=andygrove&avatarId=28239",
                            "32x32": "https://issues.apache.org/jira/secure/useravatar?size=medium&ownerId=andygrove&avatarId=28239"
                        },
                        "displayName": "Andy Grove",
                        "active": true,
                        "timeZone": "America/Denver"
                    },
                    "created": "2019-09-01T15:25:13.081+0000",
                    "updated": "2019-09-01T15:25:13.081+0000"
                }
            ],
            "maxResults": 1,
            "total": 1,
            "startAt": 0
        },
        "customfield_12311820": "0|z00a9s:",
        "customfield_12314139": null
    }
}